[
    {
        "Status": "Open",
        "CRN": "10954",
        "Course Number": "CIED 1001",
        "Section": "A",
        "Title": "Sel Topics Academic Discourse",
        "Credits": ".5",
        "Type": "Lecture",
        "Restrictions": "Yes",
        "Prerequistes": "No",
        "Instructor Name": "Susan Burhoe",
        "Meeting Date": "Meeting Date: Jan 06, 2021 to Apr 09, 2021 Days: Tue Time: 18:05 - 20:55",
        "Also Register In": "Section Information:Restricted to Students in the Enriched Support Program.",
        "Other": "none"
    }
]
