[
    {
        "Status": "Open",
        "CRN": "33776",
        "Course Number": "MAAE 2001",
        "Section": "A",
        "Title": "Engineering Graphical Design",
        "Credits": ".5",
        "Type": "Lecture",
        "Restrictions": "Yes",
        "Prerequistes": "Yes",
        "Instructor Name": "Ron Miller",
        "Meeting Date": "Meeting Date: Sep 09, 2020 to Dec 11, 2020 Days: Mon Wed Time: 08:35 - 09:25",
        "Also Register In": "Also Register in:MAAE 2001 L1",
        "Other": "Section Information:Blended course: a mixture of synchronous meetings at scheduled time and asynchronous activities. Students are expected to be available during the synchronous meeting times. This section is for 2nd yr SREE-B students. All others pleas submt an Eng Request Form."
    },
    {
        "Status": "Open",
        "CRN": "33777",
        "Course Number": "MAAE 2001",
        "Section": "L1",
        "Title": "Engineering Graphical Design",
        "Credits": "0",
        "Type": "Laboratory",
        "Restrictions": "Yes",
        "Prerequistes": "No",
        "Instructor Name": "Ron Miller",
        "Meeting Date": "Meeting Date: Sep 09, 2020 to Dec 11, 2020 Days: Tue Thu Time: 14:35 - 16:25",
        "Also Register In": "Also Register in:MAAE 2001 A",
        "Other": "Section Information:This lab is for non-Aero students only."
    },
    {
        "Status": "Full, No Waitlist",
        "CRN": "33778",
        "Course Number": "MAAE 2101",
        "Section": "A",
        "Title": "Engineering Dynamics",
        "Credits": ".5",
        "Type": "Lecture",
        "Restrictions": "Yes",
        "Prerequistes": "Yes",
        "Instructor Name": "Fred Afagh",
        "Meeting Date": "Meeting Date: Sep 09, 2020 to Dec 11, 2020 Days: Tue Thu Time: 11:35 - 12:55",
        "Also Register In": "Also Register in:MAAE 2101 L1 or L2 or L3 or L4 or L5",
        "Other": "Section Information:Precludes additional credit for CIVE 2101. Blended course: a mixture of synchronous meetings at scheduled time and asynchronouse activities. Students are expected to be available during the synchronous meeting times. available during the meeting time. This section is for 2nd yr AERO C, BIOMECH, MECH and SREE B students. All others please submit an Eng Request Form. This course is supported by Peer Assisted Study Sessions (PASS). Further information here: https://carleton.ca/csas/pass"
    },
    {
        "Status": "Open",
        "CRN": "33779",
        "Course Number": "MAAE 2101",
        "Section": "B",
        "Title": "Engineering Dynamics",
        "Credits": ".5",
        "Type": "Lecture",
        "Restrictions": "Yes",
        "Prerequistes": "Yes",
        "Instructor Name": "Fred Afagh",
        "Meeting Date": "Meeting Date: Sep 09, 2020 to Dec 11, 2020 Days: Tue Thu Time: 14:35 - 15:55",
        "Also Register In": "Also Register in:MAAE 2101 L1 or L2 or L3 or L4 or L5",
        "Other": "Section Information:Blended course: a mixture of synchronous meetings at scheduled times and asynchronous activities. Students are expected to be available during the synchronous meeting times. This section is for 2nd yr AERO D, BIOMECH, MECH and SREE B students. All others please submit an Eng Request Form. Precludes additional credit for CIVE 2101. This course will be supported by Peer Assisted Study Sessions (PASS). Further information here: https://carleton.ca/csas/pass"
    },
    {
        "Status": "Open",
        "CRN": "33780",
        "Course Number": "MAAE 2101",
        "Section": "L1",
        "Title": "Engineering Dynamics",
        "Credits": "0",
        "Type": "Problem Analysis",
        "Restrictions": "Yes",
        "Prerequistes": "No",
        "Instructor Name": "Fred Afagh",
        "Meeting Date": "Meeting Date: Sep 09, 2020 to Dec 11, 2020 Days: Fri Time: 11:35 - 14:25",
        "Also Register In": "Also Register in:MAAE 2101 A or B",
        "Other": "none"
    },
    {
        "Status": "Full, No Waitlist",
        "CRN": "33781",
        "Course Number": "MAAE 2101",
        "Section": "L2",
        "Title": "Engineering Dynamics",
        "Credits": "0",
        "Type": "Problem Analysis",
        "Restrictions": "Yes",
        "Prerequistes": "No",
        "Instructor Name": "Fred Afagh",
        "Meeting Date": "Meeting Date: Sep 09, 2020 to Dec 11, 2020 Days: Wed Time: 08:35 - 11:25",
        "Also Register In": "Also Register in:MAAE 2101 A or B",
        "Other": "none"
    },
    {
        "Status": "Full, No Waitlist",
        "CRN": "33782",
        "Course Number": "MAAE 2101",
        "Section": "L3",
        "Title": "Engineering Dynamics",
        "Credits": "0",
        "Type": "Problem Analysis",
        "Restrictions": "Yes",
        "Prerequistes": "No",
        "Instructor Name": "Fred Afagh",
        "Meeting Date": "Meeting Date: Sep 09, 2020 to Dec 11, 2020 Days: Fri Time: 08:35 - 11:25",
        "Also Register In": "Also Register in:MAAE 2101 A or B",
        "Other": "none"
    },
    {
        "Status": "Full, No Waitlist",
        "CRN": "33783",
        "Course Number": "MAAE 2101",
        "Section": "L4",
        "Title": "Engineering Dynamics",
        "Credits": "0",
        "Type": "Problem Analysis",
        "Restrictions": "Yes",
        "Prerequistes": "No",
        "Instructor Name": "Fred Afagh",
        "Meeting Date": "Meeting Date: Sep 09, 2020 to Dec 11, 2020 Days: Mon Time: 14:35 - 17:25",
        "Also Register In": "Also Register in:MAAE 2101 A or B",
        "Other": "none"
    },
    {
        "Status": "Open",
        "CRN": "33784",
        "Course Number": "MAAE 2101",
        "Section": "L5",
        "Title": "Engineering Dynamics",
        "Credits": "0",
        "Type": "Problem Analysis",
        "Restrictions": "Yes",
        "Prerequistes": "No",
        "Instructor Name": "Fred Afagh",
        "Meeting Date": "Meeting Date: Sep 09, 2020 to Dec 11, 2020 Days: Tue Time: 14:35 - 17:25",
        "Also Register In": "Also Register in:MAAE 2101 A or B",
        "Other": "none"
    },
    {
        "Status": "Full, No Waitlist",
        "CRN": "33785",
        "Course Number": "MAAE 2202",
        "Section": "A",
        "Title": "Mechanics of Solids I",
        "Credits": ".5",
        "Type": "Lecture",
        "Restrictions": "Yes",
        "Prerequistes": "Yes",
        "Instructor Name": "Oren Petel",
        "Meeting Date": "Meeting Date: Sep 09, 2020 to Dec 11, 2020 Days: Wed Fri Time: 11:35 - 12:55",
        "Also Register In": "Also Register in:MAAE 2202 L1 or L2 or L3",
        "Other": "Section Information:Precludes additional credit for CIVE 2200."
    },
    {
        "Status": "Full, No Waitlist",
        "CRN": "33786",
        "Course Number": "MAAE 2202",
        "Section": "L1",
        "Title": "Mechanics of Solids I",
        "Credits": "0",
        "Type": "Laboratory",
        "Restrictions": "Yes",
        "Prerequistes": "No",
        "Instructor Name": "Oren Petel",
        "Meeting Date": "Meeting Date: Sep 09, 2020 to Dec 11, 2020 Days: Fri Time: 08:35 - 11:25",
        "Also Register In": "Also Register in:MAAE 2202 A",
        "Other": "none"
    },
    {
        "Status": "Full, No Waitlist",
        "CRN": "33787",
        "Course Number": "MAAE 2202",
        "Section": "L2",
        "Title": "Mechanics of Solids I",
        "Credits": "0",
        "Type": "Laboratory",
        "Restrictions": "Yes",
        "Prerequistes": "No",
        "Instructor Name": "Oren Petel",
        "Meeting Date": "Meeting Date: Sep 09, 2020 to Dec 11, 2020 Days: Fri Time: 14:35 - 17:25",
        "Also Register In": "Also Register in:MAAE 2202 A",
        "Other": "none"
    },
    {
        "Status": "Full, No Waitlist",
        "CRN": "33788",
        "Course Number": "MAAE 2202",
        "Section": "L3",
        "Title": "Mechanics of Solids I",
        "Credits": "0",
        "Type": "Laboratory",
        "Restrictions": "No",
        "Prerequistes": "No",
        "Instructor Name": "Oren Petel",
        "Meeting Date": "Meeting Date: Sep 09, 2020 to Dec 11, 2020 Days: Mon Time: 14:35 - 17:25",
        "Also Register In": "Also Register in:MAAE 2202 A",
        "Other": "none"
    },
    {
        "Status": "Open",
        "CRN": "33789",
        "Course Number": "MAAE 2300",
        "Section": "A",
        "Title": "Fluid Mechanics I",
        "Credits": ".5",
        "Type": "Lecture",
        "Restrictions": "Yes",
        "Prerequistes": "Yes",
        "Instructor Name": "Fidel Khouli",
        "Meeting Date": "Meeting Date: Sep 09, 2020 to Dec 11, 2020 Days: Mon Wed Time: 08:35 - 09:55",
        "Also Register In": "Also Register in:MAAE 2300 L1 or L2 or L3 or L4 or L5 or L6 or L7",
        "Other": "Section Information:Lectures will be delivered asynchronously according to a schedule provided by the instructor. Using web conferencing tools, scheduled meeting times wil be used to answer questions about the lecture, solve additional problems, hold office hours and conduct midterms. PA sessions and labs will be synchronous via web conferencing tools. Students are expected to be available during their PA session meeting time. All synchronously held parts of the course will be recorded and available online. This is section is for 2nd yr AERO A, B, D, CIVE and ENVE and 3rd yr AERO C students. All others please submit an Eng Request Form. This course will be supported by Peer Assisted Study Sessions (PASS). Further information here:  https://carleton.ca/csas/pass"
    },
    {
        "Status": "Open",
        "CRN": "33790",
        "Course Number": "MAAE 2300",
        "Section": "B",
        "Title": "Fluid Mechanics I",
        "Credits": ".5",
        "Type": "Lecture",
        "Restrictions": "Yes",
        "Prerequistes": "Yes",
        "Instructor Name": "Nafisa Bano",
        "Meeting Date": "Meeting Date: Sep 09, 2020 to Dec 11, 2020 Days: Tue Thu Time: 13:05 - 14:25",
        "Also Register In": "Also Register in:MAAE 2300 L1 or L2 or L3 or L4 or L5 or L6 or L7",
        "Other": "Section Information:This section is for 2nd yr AERO A, B, D, CIVE, ENVE and 3rd yr AERO C students. All others please submit an Eng Request Form. This course will be supported by Peer Assisted Study Sessions (PASS). Further information here:  https://carleton.ca/csas/pass"
    },
    {
        "Status": "Full, No Waitlist",
        "CRN": "33791",
        "Course Number": "MAAE 2300",
        "Section": "C",
        "Title": "Fluid Mechanics I",
        "Credits": ".5",
        "Type": "Lecture",
        "Restrictions": "Yes",
        "Prerequistes": "Yes",
        "Instructor Name": "Reza Kholghy",
        "Meeting Date": "Meeting Date: Sep 09, 2020 to Dec 11, 2020 Days: Mon Wed Time: 10:05 - 11:25",
        "Also Register In": "Also Register in:MAAE 2300 L1 or L2 or L3 or L4 or L5 or L6 or L7",
        "Other": "Section Information:This section is for 2nd yr AERO A, D, CIVE, ENVE and 3rd yr AERO C students. All others please submit an Eng Request Form. The lectures will be delivered asynchronusly. The recorded lecture will be posted the day before the schedule meeting time. Using web conferencing, scheduled meeting time will be used to answer questions, solve additional problems, hold office hours and conduct midterm tests. Students are encouraged to participate during the scheduled meeting time. Additional activities, assignments and suggested problems be available via the course web page. PA sessions and labs will be conducted synchronously at their scheduled meeting times. Students are expected to be available during the PA session. All synchronously held parts of the course will be recorded and available online. This course will be supported by Peer Assisted Study Sessions (PASS). Further information here:  https://carleton.ca/csas/pass"
    },
    {
        "Status": "Full, No Waitlist",
        "CRN": "33792",
        "Course Number": "MAAE 2300",
        "Section": "L1",
        "Title": "Fluid Mechanics I",
        "Credits": "0",
        "Type": "Laboratory",
        "Restrictions": "Yes",
        "Prerequistes": "No",
        "Instructor Name": "Fidel Khouli",
        "Meeting Date": "Meeting Date: Sep 09, 2020 to Dec 11, 2020 Days: Mon Time: 11:35 - 14:25",
        "Also Register In": "Also Register in:MAAE 2300 A or B or C",
        "Other": "none"
    },
    {
        "Status": "Open",
        "CRN": "33793",
        "Course Number": "MAAE 2300",
        "Section": "L2",
        "Title": "Fluid Mechanics I",
        "Credits": "0",
        "Type": "Laboratory",
        "Restrictions": "No",
        "Prerequistes": "No",
        "Instructor Name": "Fidel Khouli",
        "Meeting Date": "Meeting Date: Sep 09, 2020 to Dec 11, 2020 Days: Wed Time: 11:35 - 14:25",
        "Also Register In": "Also Register in:MAAE 2300 A or B or C",
        "Other": "none"
    },
    {
        "Status": "Full, No Waitlist",
        "CRN": "33794",
        "Course Number": "MAAE 2300",
        "Section": "L3",
        "Title": "Fluid Mechanics I",
        "Credits": "0",
        "Type": "Laboratory",
        "Restrictions": "Yes",
        "Prerequistes": "No",
        "Instructor Name": "Fidel Khouli",
        "Meeting Date": "Meeting Date: Sep 09, 2020 to Dec 11, 2020 Days: Thu Time: 14:35 - 17:25",
        "Also Register In": "Also Register in:MAAE 2300 A or B or C",
        "Other": "none"
    },
    {
        "Status": "Full, No Waitlist",
        "CRN": "33795",
        "Course Number": "MAAE 2300",
        "Section": "L4",
        "Title": "Fluid Mechanics I",
        "Credits": "0",
        "Type": "Laboratory",
        "Restrictions": "No",
        "Prerequistes": "No",
        "Instructor Name": "Fidel Khouli",
        "Meeting Date": "Meeting Date: Sep 09, 2020 to Dec 11, 2020 Days: Tue Time: 14:35 - 17:25",
        "Also Register In": "Also Register in:MAAE 2300 A or B or C",
        "Other": "none"
    },
    {
        "Status": "Full, No Waitlist",
        "CRN": "33796",
        "Course Number": "MAAE 2300",
        "Section": "L5",
        "Title": "Fluid Mechanics I",
        "Credits": "0",
        "Type": "Laboratory",
        "Restrictions": "No",
        "Prerequistes": "No",
        "Instructor Name": "Fidel Khouli",
        "Meeting Date": "Meeting Date: Sep 09, 2020 to Dec 11, 2020 Days: Wed Time: 14:35 - 17:25",
        "Also Register In": "Also Register in:MAAE 2300 A or B or C",
        "Other": "none"
    },
    {
        "Status": "Full, No Waitlist",
        "CRN": "33797",
        "Course Number": "MAAE 2300",
        "Section": "L6",
        "Title": "Fluid Mechanics I",
        "Credits": "0",
        "Type": "Laboratory",
        "Restrictions": "No",
        "Prerequistes": "No",
        "Instructor Name": "Fidel Khouli",
        "Meeting Date": "Meeting Date: Sep 09, 2020 to Dec 11, 2020 Days: Fri Time: 08:35 - 11:25",
        "Also Register In": "Also Register in:MAAE 2300 A or B or C",
        "Other": "none"
    },
    {
        "Status": "Full, No Waitlist",
        "CRN": "33798",
        "Course Number": "MAAE 2300",
        "Section": "L7",
        "Title": "Fluid Mechanics I",
        "Credits": "0",
        "Type": "Laboratory",
        "Restrictions": "No",
        "Prerequistes": "No",
        "Instructor Name": "Fidel Khouli",
        "Meeting Date": "Meeting Date: Sep 09, 2020 to Dec 11, 2020 Days: Fri Time: 14:35 - 17:25",
        "Also Register In": "Also Register in:MAAE 2300 A or B or C",
        "Other": "none"
    },
    {
        "Status": "Full, No Waitlist",
        "CRN": "33799",
        "Course Number": "MAAE 2400",
        "Section": "A",
        "Title": "Thermodynamics & Heat Transfer",
        "Credits": ".5",
        "Type": "Lecture",
        "Restrictions": "Yes",
        "Prerequistes": "Yes",
        "Instructor Name": "Ian Beausoleil-Morrison",
        "Meeting Date": "Meeting Date: Sep 09, 2020 to Dec 11, 2020 Days: Mon Wed Time: 13:05 - 14:25",
        "Also Register In": "Also Register in:MAAE 2400 L1 or L2 or L3 or L4 or L5 or L6 or L7 or L8",
        "Other": "Section Information:This section is for 2nd yr BIOMECH, ENVE, MECH , SREE A and B students. All others please submit an Eng Request Form. This course will be supported by Peer Assisted Study Sessions (PASS). Further information here:  https://carleton.ca/csas/pass"
    },
    {
        "Status": "Open",
        "CRN": "33800",
        "Course Number": "MAAE 2400",
        "Section": "B",
        "Title": "Thermodynamics & Heat Transfer",
        "Credits": ".5",
        "Type": "Lecture",
        "Restrictions": "Yes",
        "Prerequistes": "Yes",
        "Instructor Name": "Cynthia Cruickshank",
        "Meeting Date": "Meeting Date: Sep 09, 2020 to Dec 11, 2020 Days: Tue Thu Time: 11:35 - 12:55",
        "Also Register In": "Also Register in:MAAE 2400 L1 or L2 or L3 or L4 or L5 or L6 or L7 or L8",
        "Other": "Section Information:This section is for 2nd yr BIOMECH, ENVE, MECH , SREE A and B students. All others please submit an Eng Req Form. This course will be supported by Peer Assisted Study Sessions (PASS). Further information here:  https://carleton.ca/csas/pass"
    },
    {
        "Status": "Full, No Waitlist",
        "CRN": "33801",
        "Course Number": "MAAE 2400",
        "Section": "C",
        "Title": "Thermodynamics & Heat Transfer",
        "Credits": ".5",
        "Type": "Lecture",
        "Restrictions": "Yes",
        "Prerequistes": "Yes",
        "Instructor Name": "Vinh Tang",
        "Meeting Date": "Meeting Date: Sep 09, 2020 to Dec 11, 2020 Days: Tue Thu Time: 13:05 - 14:25",
        "Also Register In": "Also Register in:MAAE 2400 L1 or L2 or L3 or L4 or L5 or L6 or L7 or L8",
        "Other": "Section Information:This section is for 2nd yr BIOMECH, ENVE, MECH , SREE A and B students. All others please submit an Eng Request Form. This course will be supported by Peer Assisted Study Sessions (PASS). Further information here:  https://carleton.ca/csas/pass"
    },
    {
        "Status": "Full, No Waitlist",
        "CRN": "33802",
        "Course Number": "MAAE 2400",
        "Section": "L1",
        "Title": "Thermodynamics & Heat Transfer",
        "Credits": "0",
        "Type": "Laboratory",
        "Restrictions": "Yes",
        "Prerequistes": "No",
        "Instructor Name": "Ian Beausoleil-Morrison",
        "Meeting Date": "Meeting Date: Sep 09, 2020 to Dec 11, 2020 Days: Fri Time: 08:35 - 11:25",
        "Also Register In": "Also Register in:MAAE 2400 A or B or C",
        "Other": "none"
    },
    {
        "Status": "Full, No Waitlist",
        "CRN": "33803",
        "Course Number": "MAAE 2400",
        "Section": "L2",
        "Title": "Thermodynamics & Heat Transfer",
        "Credits": "0",
        "Type": "Laboratory",
        "Restrictions": "Yes",
        "Prerequistes": "No",
        "Instructor Name": "Ian Beausoleil-Morrison",
        "Meeting Date": "Meeting Date: Sep 09, 2020 to Dec 11, 2020 Days: Thu Time: 08:35 - 11:25",
        "Also Register In": "Also Register in:MAAE 2400 A or B or C",
        "Other": "none"
    },
    {
        "Status": "Full, No Waitlist",
        "CRN": "33804",
        "Course Number": "MAAE 2400",
        "Section": "L3",
        "Title": "Thermodynamics & Heat Transfer",
        "Credits": "0",
        "Type": "Laboratory",
        "Restrictions": "No",
        "Prerequistes": "No",
        "Instructor Name": "Ian Beausoleil-Morrison",
        "Meeting Date": "Meeting Date: Sep 09, 2020 to Dec 11, 2020 Days: Fri Time: 14:35 - 17:25",
        "Also Register In": "Also Register in:MAAE 2400 A or B or C",
        "Other": "none"
    },
    {
        "Status": "Full, No Waitlist",
        "CRN": "33805",
        "Course Number": "MAAE 2400",
        "Section": "L4",
        "Title": "Thermodynamics & Heat Transfer",
        "Credits": "0",
        "Type": "Laboratory",
        "Restrictions": "Yes",
        "Prerequistes": "No",
        "Instructor Name": "Ian Beausoleil-Morrison",
        "Meeting Date": "Meeting Date: Sep 09, 2020 to Dec 11, 2020 Days: Tue Time: 08:35 - 11:25",
        "Also Register In": "Also Register in:MAAE 2400 A or B or C",
        "Other": "none"
    },
    {
        "Status": "Full, No Waitlist",
        "CRN": "33806",
        "Course Number": "MAAE 2400",
        "Section": "L5",
        "Title": "Thermodynamics & Heat Transfer",
        "Credits": "0",
        "Type": "Laboratory",
        "Restrictions": "Yes",
        "Prerequistes": "No",
        "Instructor Name": "Ian Beausoleil-Morrison",
        "Meeting Date": "Meeting Date: Sep 09, 2020 to Dec 11, 2020 Days: Mon Time: 08:35 - 11:25",
        "Also Register In": "Also Register in:MAAE 2400 A or B or C",
        "Other": "none"
    },
    {
        "Status": "Open",
        "CRN": "33807",
        "Course Number": "MAAE 2400",
        "Section": "L6",
        "Title": "Thermodynamics & Heat Transfer",
        "Credits": "0",
        "Type": "Laboratory",
        "Restrictions": "Yes",
        "Prerequistes": "No",
        "Instructor Name": "Ian Beausoleil-Morrison",
        "Meeting Date": "Meeting Date: Sep 09, 2020 to Dec 11, 2020 Days: Wed Time: 08:35 - 11:25",
        "Also Register In": "Also Register in:MAAE 2400 A or B or C",
        "Other": "none"
    },
    {
        "Status": "Full, No Waitlist",
        "CRN": "33808",
        "Course Number": "MAAE 2400",
        "Section": "L7",
        "Title": "Thermodynamics & Heat Transfer",
        "Credits": "0",
        "Type": "Laboratory",
        "Restrictions": "Yes",
        "Prerequistes": "No",
        "Instructor Name": "Ian Beausoleil-Morrison",
        "Meeting Date": "Meeting Date: Sep 09, 2020 to Dec 11, 2020 Days: Thu Time: 14:35 - 17:25",
        "Also Register In": "Also Register in:MAAE 2400 A or B or C",
        "Other": "none"
    },
    {
        "Status": "Full, No Waitlist",
        "CRN": "33809",
        "Course Number": "MAAE 2400",
        "Section": "L8",
        "Title": "Thermodynamics & Heat Transfer",
        "Credits": "0",
        "Type": "Laboratory",
        "Restrictions": "Yes",
        "Prerequistes": "No",
        "Instructor Name": "Ian Beausoleil-Morrison",
        "Meeting Date": "Meeting Date: Sep 09, 2020 to Dec 11, 2020 Days: Mon Time: 14:35 - 17:25",
        "Also Register In": "Also Register in:MAAE 2400 A or B or C",
        "Other": "none"
    },
    {
        "Status": "Open",
        "CRN": "33810",
        "Course Number": "MAAE 2700",
        "Section": "A",
        "Title": "Engineering Materials",
        "Credits": ".5",
        "Type": "Lecture",
        "Restrictions": "Yes",
        "Prerequistes": "Yes",
        "Instructor Name": "Abu Syed Kabir",
        "Meeting Date": "Meeting Date: Sep 09, 2020 to Dec 11, 2020 Days: Tue Thu Time: 10:05 - 11:25",
        "Also Register In": "Also Register in:MAAE 2700 L1 or L2 or L3 or L4 or L5 or L6",
        "Other": "Section Information:Precludes additional credit for CIVE 2700. This course will be delivered asynchronously. Students will access materials and complete activities on their own time based on structure and guidance provided by the instructor. Meeting time will be used for office hours and the midterm."
    },
    {
        "Status": "Open",
        "CRN": "33811",
        "Course Number": "MAAE 2700",
        "Section": "B",
        "Title": "Engineering Materials",
        "Credits": ".5",
        "Type": "Lecture",
        "Restrictions": "Yes",
        "Prerequistes": "Yes",
        "Instructor Name": "Abu Syed Kabir",
        "Meeting Date": "Meeting Date: Sep 09, 2020 to Dec 11, 2020 Days: Wed Fri Time: 11:35 - 12:55",
        "Also Register In": "Also Register in:MAAE 2700 L1 or L2 or L3 or L4 or L5 or L6",
        "Other": "Section Information:Precludes additional credit for CIVE 2700. This course will be delivered asynchronously. Students will access materials and complete activities on their own time based on structure and guidance provided by the instructor. Meeting time will be used for office hours and the midterm."
    },
    {
        "Status": "Full, No Waitlist",
        "CRN": "33812",
        "Course Number": "MAAE 2700",
        "Section": "L1",
        "Title": "Engineering Materials",
        "Credits": "0",
        "Type": "Laboratory",
        "Restrictions": "Yes",
        "Prerequistes": "No",
        "Instructor Name": "Abu Syed Kabir",
        "Meeting Date": "Meeting Date: Sep 09, 2020 to Dec 11, 2020 Days: Mon Time: 08:35 - 11:25",
        "Also Register In": "Also Register in:MAAE 2700 A or B",
        "Other": "none"
    },
    {
        "Status": "Full, No Waitlist",
        "CRN": "33813",
        "Course Number": "MAAE 2700",
        "Section": "L2",
        "Title": "Engineering Materials",
        "Credits": "0",
        "Type": "Laboratory",
        "Restrictions": "Yes",
        "Prerequistes": "No",
        "Instructor Name": "Abu Syed Kabir",
        "Meeting Date": "Meeting Date: Sep 09, 2020 to Dec 11, 2020 Days: Wed Time: 08:35 - 11:25",
        "Also Register In": "Also Register in:MAAE 2700 A or B",
        "Other": "none"
    },
    {
        "Status": "Full, No Waitlist",
        "CRN": "33814",
        "Course Number": "MAAE 2700",
        "Section": "L3",
        "Title": "Engineering Materials",
        "Credits": "0",
        "Type": "Laboratory",
        "Restrictions": "Yes",
        "Prerequistes": "No",
        "Instructor Name": "Abu Syed Kabir",
        "Meeting Date": "Meeting Date: Sep 09, 2020 to Dec 11, 2020 Days: Mon Time: 14:35 - 17:25",
        "Also Register In": "Also Register in:MAAE 2700 A or B",
        "Other": "none"
    },
    {
        "Status": "Full, No Waitlist",
        "CRN": "33815",
        "Course Number": "MAAE 2700",
        "Section": "L4",
        "Title": "Engineering Materials",
        "Credits": "0",
        "Type": "Laboratory",
        "Restrictions": "Yes",
        "Prerequistes": "No",
        "Instructor Name": "Abu Syed Kabir",
        "Meeting Date": "Meeting Date: Sep 09, 2020 to Dec 11, 2020 Days: Fri Time: 08:35 - 11:25",
        "Also Register In": "Also Register in:MAAE 2700 A or B",
        "Other": "none"
    },
    {
        "Status": "Full, No Waitlist",
        "CRN": "33816",
        "Course Number": "MAAE 2700",
        "Section": "L5",
        "Title": "Engineering Materials",
        "Credits": "0",
        "Type": "Laboratory",
        "Restrictions": "Yes",
        "Prerequistes": "No",
        "Instructor Name": "Abu Syed Kabir",
        "Meeting Date": "Meeting Date: Sep 09, 2020 to Dec 11, 2020 Days: Tue Time: 08:35 - 11:25",
        "Also Register In": "Also Register in:MAAE 2700 A or B",
        "Other": "none"
    },
    {
        "Status": "Full, No Waitlist",
        "CRN": "33817",
        "Course Number": "MAAE 2700",
        "Section": "L6",
        "Title": "Engineering Materials",
        "Credits": "0",
        "Type": "Laboratory",
        "Restrictions": "Yes",
        "Prerequistes": "No",
        "Instructor Name": "Abu Syed Kabir",
        "Meeting Date": "Meeting Date: Sep 09, 2020 to Dec 11, 2020 Days: Mon Time: 11:35 - 14:25",
        "Also Register In": "Also Register in:MAAE 2700 A or B",
        "Other": "none"
    },
    {
        "Status": "Open",
        "CRN": "33818",
        "Course Number": "MAAE 3004",
        "Section": "A",
        "Title": "Dynamics of Machinery",
        "Credits": ".5",
        "Type": "Lecture",
        "Restrictions": "Yes",
        "Prerequistes": "Yes",
        "Instructor Name": "John Hayes",
        "Meeting Date": "Meeting Date: Sep 09, 2020 to Dec 11, 2020 Days: Tue Thu Time: 11:35 - 12:55",
        "Also Register In": "Also Register in:MAAE 3004 L1 or L2 or L3 or L4",
        "Other": "Section Information:This section is for 3rd yr AERO A,B,C and BIOMECH students. All others please submit an Eng Request Form. . Lectures will be delivered asynchronousely. Students wil access materials and completed activities according to a posted schedule. Meeting time will be used for office hours and the midterm. Students are expected to be available during the meeting time. This course will be supported by Peer Assisted Study Sessions (PASS). Further information here:  https://carleton.ca/csas/pass"
    },
    {
        "Status": "Open",
        "CRN": "33819",
        "Course Number": "MAAE 3004",
        "Section": "B",
        "Title": "Dynamics of Machinery",
        "Credits": ".5",
        "Type": "Lecture",
        "Restrictions": "Yes",
        "Prerequistes": "Yes",
        "Instructor Name": "John Hayes",
        "Meeting Date": "Meeting Date: Sep 09, 2020 to Dec 11, 2020 Days: Wed Fri Time: 10:05 - 11:25",
        "Also Register In": "Also Register in:MAAE 3004 L1 or L2 or L3 or L4",
        "Other": "Section Information:Lectures will be delivered asynchronously. Students will access materials and completed activities according to a posted schedule. Meeting time will be used for office hours and the midterm. Students are expected to be available during the meeting time. This section is for 3rd yr AERO A,B,D and BIOMEC students. All others please submit an Eng Request Form. This course will be supported by Peer Assisted Study Sessions (PASS). Further information here:  https://carleton.ca/csas/pass"
    },
    {
        "Status": "Full, No Waitlist",
        "CRN": "33820",
        "Course Number": "MAAE 3004",
        "Section": "L1",
        "Title": "Dynamics of Machinery",
        "Credits": "0",
        "Type": "Tutorial",
        "Restrictions": "Yes",
        "Prerequistes": "No",
        "Instructor Name": "John Hayes",
        "Meeting Date": "Meeting Date: Sep 09, 2020 to Dec 11, 2020 Days: Mon Time: 11:35 - 13:25",
        "Also Register In": "Also Register in:MAAE 3004 A or B",
        "Other": "none"
    },
    {
        "Status": "Open",
        "CRN": "33821",
        "Course Number": "MAAE 3004",
        "Section": "L2",
        "Title": "Dynamics of Machinery",
        "Credits": "0",
        "Type": "Tutorial",
        "Restrictions": "Yes",
        "Prerequistes": "No",
        "Instructor Name": "John Hayes",
        "Meeting Date": "Meeting Date: Sep 09, 2020 to Dec 11, 2020 Days: Fri Time: 08:35 - 10:25",
        "Also Register In": "Also Register in:MAAE 3004 A or B",
        "Other": "none"
    },
    {
        "Status": "Open",
        "CRN": "33822",
        "Course Number": "MAAE 3004",
        "Section": "L3",
        "Title": "Dynamics of Machinery",
        "Credits": "0",
        "Type": "Tutorial",
        "Restrictions": "No",
        "Prerequistes": "No",
        "Instructor Name": "John Hayes",
        "Meeting Date": "Meeting Date: Sep 09, 2020 to Dec 11, 2020 Days: Thu Time: 14:35 - 16:25",
        "Also Register In": "Also Register in:MAAE 3004 A or B",
        "Other": "none"
    },
    {
        "Status": "Open",
        "CRN": "33823",
        "Course Number": "MAAE 3004",
        "Section": "L4",
        "Title": "Dynamics of Machinery",
        "Credits": "0",
        "Type": "Tutorial",
        "Restrictions": "No",
        "Prerequistes": "No",
        "Instructor Name": "John Hayes",
        "Meeting Date": "Meeting Date: Sep 09, 2020 to Dec 11, 2020 Days: Thu Time: 15:35 - 17:25",
        "Also Register In": "Also Register in:MAAE 3004 A or B",
        "Other": "none"
    },
    {
        "Status": "Open",
        "CRN": "33824",
        "Course Number": "MAAE 3202",
        "Section": "A",
        "Title": "Mechanics of Solids II",
        "Credits": ".5",
        "Type": "Lecture",
        "Restrictions": "Yes",
        "Prerequistes": "Yes",
        "Instructor Name": "Rong Liu",
        "Meeting Date": "Meeting Date: Sep 09, 2020 to Dec 11, 2020 Days: Wed Fri Time: 14:35 - 15:55",
        "Also Register In": "Also Register in:MAAE 3202 L1 or L2 or L3 or L4",
        "Other": "Section Information:Precludes additional credit for CIVE 3202. This section is for 3rd yr BIOMECH, MECH and AERO B students. All others please submit an Eng Request Form. . This course will be taught synchronously. Students are expected to participate during the synchronous meeting time which will be recorded. This course will be supported by Peer Assisted Study Sessions (PASS). Further information here:  https://carleton.ca/csas/pass"
    },
    {
        "Status": "Open",
        "CRN": "33825",
        "Course Number": "MAAE 3202",
        "Section": "B",
        "Title": "Mechanics of Solids II",
        "Credits": ".5",
        "Type": "Lecture",
        "Restrictions": "Yes",
        "Prerequistes": "Yes",
        "Instructor Name": "Rong Liu",
        "Meeting Date": "Meeting Date: Sep 09, 2020 to Dec 11, 2020 Days: Tue Thu Time: 08:35 - 09:55",
        "Also Register In": "Also Register in:MAAE 3202 L1 or L2 or L3 or L4",
        "Other": "Section Information:Precludes additional credit for CIVE 3202. This course will be taught synchronously. Students are expected to participate during the synchronous meeting time which will be recorded. This section is for 3rd yr BIOMECH, MECH and AERO B students. All others please submit an Eng. Request Form. This course will be supported by Peer Assisted Study Sessions (PASS). Further information here: https://carleton.ca/csas/pass"
    },
    {
        "Status": "Open",
        "CRN": "33826",
        "Course Number": "MAAE 3202",
        "Section": "L1",
        "Title": "Mechanics of Solids II",
        "Credits": "0",
        "Type": "Laboratory",
        "Restrictions": "Yes",
        "Prerequistes": "No",
        "Instructor Name": "Rong Liu",
        "Meeting Date": "Meeting Date: Sep 09, 2020 to Dec 11, 2020 Days: Fri Time: 11:35 - 14:25",
        "Also Register In": "Also Register in:MAAE 3202 A or B",
        "Other": "none"
    },
    {
        "Status": "Full, No Waitlist",
        "CRN": "33827",
        "Course Number": "MAAE 3202",
        "Section": "L2",
        "Title": "Mechanics of Solids II",
        "Credits": "0",
        "Type": "Laboratory",
        "Restrictions": "Yes",
        "Prerequistes": "No",
        "Instructor Name": "Rong Liu",
        "Meeting Date": "Meeting Date: Sep 09, 2020 to Dec 11, 2020 Days: Mon Time: 08:35 - 11:25",
        "Also Register In": "Also Register in:MAAE 3202 A or B",
        "Other": "none"
    },
    {
        "Status": "Open",
        "CRN": "33828",
        "Course Number": "MAAE 3202",
        "Section": "L3",
        "Title": "Mechanics of Solids II",
        "Credits": "0",
        "Type": "Laboratory",
        "Restrictions": "Yes",
        "Prerequistes": "No",
        "Instructor Name": "Rong Liu",
        "Meeting Date": "Meeting Date: Sep 09, 2020 to Dec 11, 2020 Days: Tue Time: 14:35 - 17:25",
        "Also Register In": "Also Register in:MAAE 3202 A or B",
        "Other": "none"
    },
    {
        "Status": "Open",
        "CRN": "33829",
        "Course Number": "MAAE 3202",
        "Section": "L4",
        "Title": "Mechanics of Solids II",
        "Credits": "0",
        "Type": "Laboratory",
        "Restrictions": "Yes",
        "Prerequistes": "No",
        "Instructor Name": "Rong Liu",
        "Meeting Date": "Meeting Date: Sep 09, 2020 to Dec 11, 2020 Days: Wed Time: 11:35 - 14:25",
        "Also Register In": "Also Register in:MAAE 3202 A or B",
        "Other": "none"
    },
    {
        "Status": "Full, No Waitlist",
        "CRN": "33830",
        "Course Number": "MAAE 3300",
        "Section": "A",
        "Title": "Fluid Mechanics II",
        "Credits": ".5",
        "Type": "Lecture",
        "Restrictions": "Yes",
        "Prerequistes": "Yes",
        "Instructor Name": "Joana Torres Da Rocha",
        "Meeting Date": "Meeting Date: Sep 09, 2020 to Dec 11, 2020 Days: Tue Thu Time: 14:35 - 15:55",
        "Also Register In": "Also Register in:MAAE 3300 L1 or L2 or L3 or L4 or L5 or L6 or L7 or L8",
        "Other": "Section Information:This course will be delivered following a blended approach. Students will access materials online according to the cours schedule. Questions will be answered via email and/or at scheduled synchronous times. Students are expected to be available during the synchronous meeting times. Students will complete activies on their own time based on structure, schedule and guidance provided by the instructor or TA. This section is for 3rd yr AERO A and MECH students. All others please submit and Eng Request Form."
    },
    {
        "Status": "Open",
        "CRN": "33831",
        "Course Number": "MAAE 3300",
        "Section": "B",
        "Title": "Fluid Mechanics II",
        "Credits": ".5",
        "Type": "Lecture",
        "Restrictions": "Yes",
        "Prerequistes": "Yes",
        "Instructor Name": "John Gaydos",
        "Meeting Date": "Meeting Date: Sep 09, 2020 to Dec 11, 2020 Days: Wed Fri Time: 14:35 - 15:55",
        "Also Register In": "Also Register in:MAAE 3300 L1 or L2 or L3 or L4 or L5 or L6 or L7 or L8",
        "Other": "Section Information:This section is for 3rd yr AERO A and MECH students. All others please submit an Eng Request Form."
    },
    {
        "Status": "Full, No Waitlist",
        "CRN": "33832",
        "Course Number": "MAAE 3300",
        "Section": "L1",
        "Title": "Fluid Mechanics II",
        "Credits": "0",
        "Type": "Laboratory",
        "Restrictions": "Yes",
        "Prerequistes": "No",
        "Instructor Name": "Joana Torres Da Rocha",
        "Meeting Date": "Meeting Date: Sep 09, 2020 to Dec 11, 2020 Days: Fri Time: 11:35 - 14:25",
        "Also Register In": "Also Register in:MAAE 3300 A or B",
        "Other": "none"
    },
    {
        "Status": "Full, No Waitlist",
        "CRN": "33833",
        "Course Number": "MAAE 3300",
        "Section": "L2",
        "Title": "Fluid Mechanics II",
        "Credits": "0",
        "Type": "Laboratory",
        "Restrictions": "Yes",
        "Prerequistes": "No",
        "Instructor Name": "Joana Torres Da Rocha",
        "Meeting Date": "Meeting Date: Sep 09, 2020 to Dec 11, 2020 Days: Thu Time: 08:35 - 11:25",
        "Also Register In": "Also Register in:MAAE 3300 A or B",
        "Other": "none"
    },
    {
        "Status": "Open",
        "CRN": "33834",
        "Course Number": "MAAE 3300",
        "Section": "L3",
        "Title": "Fluid Mechanics II",
        "Credits": "0",
        "Type": "Laboratory",
        "Restrictions": "Yes",
        "Prerequistes": "No",
        "Instructor Name": "Joana Torres Da Rocha",
        "Meeting Date": "Meeting Date: Sep 09, 2020 to Dec 11, 2020 Days: Mon Time: 08:35 - 11:25",
        "Also Register In": "Also Register in:MAAE 3300 A or B",
        "Other": "none"
    },
    {
        "Status": "Full, No Waitlist",
        "CRN": "33835",
        "Course Number": "MAAE 3300",
        "Section": "L4",
        "Title": "Fluid Mechanics II",
        "Credits": "0",
        "Type": "Laboratory",
        "Restrictions": "Yes",
        "Prerequistes": "No",
        "Instructor Name": "Joana Torres Da Rocha",
        "Meeting Date": "Meeting Date: Sep 09, 2020 to Dec 11, 2020 Days: Mon Time: 14:35 - 17:25",
        "Also Register In": "Also Register in:MAAE 3300 A or B",
        "Other": "none"
    },
    {
        "Status": "Open",
        "CRN": "33836",
        "Course Number": "MAAE 3300",
        "Section": "L5",
        "Title": "Fluid Mechanics II",
        "Credits": "0",
        "Type": "Laboratory",
        "Restrictions": "Yes",
        "Prerequistes": "No",
        "Instructor Name": "Joana Torres Da Rocha",
        "Meeting Date": "Meeting Date: Sep 09, 2020 to Dec 11, 2020 Days: Tue Time: 11:35 - 14:25",
        "Also Register In": "Also Register in:MAAE 3300 A or B",
        "Other": "none"
    },
    {
        "Status": "Open",
        "CRN": "33837",
        "Course Number": "MAAE 3300",
        "Section": "L6",
        "Title": "Fluid Mechanics II",
        "Credits": "0",
        "Type": "Laboratory",
        "Restrictions": "Yes",
        "Prerequistes": "No",
        "Instructor Name": "Joana Torres Da Rocha",
        "Meeting Date": "Meeting Date: Sep 09, 2020 to Dec 11, 2020 Days: Thu Time: 11:35 - 14:25",
        "Also Register In": "Also Register in:MAAE 3300 A or B",
        "Other": "none"
    },
    {
        "Status": "Open",
        "CRN": "33838",
        "Course Number": "MAAE 3300",
        "Section": "L7",
        "Title": "Fluid Mechanics II",
        "Credits": "0",
        "Type": "Laboratory",
        "Restrictions": "Yes",
        "Prerequistes": "No",
        "Instructor Name": "Joana Torres Da Rocha",
        "Meeting Date": "Meeting Date: Sep 09, 2020 to Dec 11, 2020 Days: Tue Time: 08:35 - 11:25",
        "Also Register In": "Also Register in:MAAE 3300 A or B",
        "Other": "none"
    },
    {
        "Status": "Full, No Waitlist",
        "CRN": "33839",
        "Course Number": "MAAE 3300",
        "Section": "L8",
        "Title": "Fluid Mechanics II",
        "Credits": "0",
        "Type": "Laboratory",
        "Restrictions": "Yes",
        "Prerequistes": "No",
        "Instructor Name": "Joana Torres Da Rocha",
        "Meeting Date": "Meeting Date: Sep 09, 2020 to Dec 11, 2020 Days: Wed Time: 08:35 - 11:25",
        "Also Register In": "Also Register in:MAAE 3300 A or B",
        "Other": "none"
    },
    {
        "Status": "Open",
        "CRN": "33841",
        "Course Number": "MAAE 4102",
        "Section": "A",
        "Title": "Materials: Strength & Fracture",
        "Credits": ".5",
        "Type": "Lecture",
        "Restrictions": "Yes",
        "Prerequistes": "Yes",
        "Instructor Name": "Suraj Joshi",
        "Meeting Date": "Meeting Date: Sep 09, 2020 to Dec 11, 2020 Days: Wed Time: 18:05 - 20:55",
        "Also Register In": "Section Information:This course is for 4th yr students. All others please submit an Eng Request Form.",
        "Other": "none"
    },
    {
        "Status": "Open",
        "CRN": "33842",
        "Course Number": "MAAE 4907",
        "Section": "A",
        "Title": "Engineering Design Project",
        "Credits": ".5",
        "Type": "Laboratory",
        "Restrictions": "No",
        "Prerequistes": "No",
        "Instructor Name": "John Gaydos",
        "Meeting Date": "Meeting Date: Sep 09, 2020 to Dec 11, 2020 Days: Mon Time: 08:35 - 11:25",
        "Also Register In": "Meeting Date: Sep 09, 2020 to Dec 11, 2020 Days: Fri Time: 10:05 - 11:25",
        "Other": "Also Register in:MAAE 4907 T1",
        "none": "Section Information:Advanced Aircraft Design Blended course: a mixture of synchronous meetings at scheduled time and asynchronous activities. Students are expected to be available during the synchronous meeting times."
    },
    {
        "Status": "Open",
        "CRN": "33843",
        "Course Number": "MAAE 4907",
        "Section": "B",
        "Title": "Engineering Design Project",
        "Credits": ".5",
        "Type": "Laboratory",
        "Restrictions": "Yes",
        "Prerequistes": "No",
        "Instructor Name": "John Gaydos",
        "Meeting Date": "Meeting Date: Sep 09, 2020 to Dec 11, 2020 Days: Mon Time: 10:05 - 11:25",
        "Also Register In": "Meeting Date: Sep 09, 2020 to Dec 11, 2020 Days: Fri Time: 08:35 - 11:25",
        "Other": "Also Register in:MAAE 4907 T1",
        "none": "Section Information:Satellite Design Project"
    },
    {
        "Status": "Open",
        "CRN": "33844",
        "Course Number": "MAAE 4907",
        "Section": "C",
        "Title": "Engineering Design Project",
        "Credits": ".5",
        "Type": "Laboratory",
        "Restrictions": "Yes",
        "Prerequistes": "No",
        "Instructor Name": "John Gaydos",
        "Meeting Date": "Meeting Date: Sep 09, 2020 to Dec 11, 2020 Days: Mon Time: 10:05 - 11:25",
        "Also Register In": "Meeting Date: Sep 09, 2020 to Dec 11, 2020 Days: Fri Time: 08:35 - 11:25",
        "Other": "Also Register in:MAAE 4907 T1",
        "none": "Section Information:Blended Wing-UAV"
    },
    {
        "Status": "Open",
        "CRN": "33845",
        "Course Number": "MAAE 4907",
        "Section": "D",
        "Title": "Engineering Design Project",
        "Credits": ".5",
        "Type": "Laboratory",
        "Restrictions": "Yes",
        "Prerequistes": "No",
        "Instructor Name": "John Gaydos",
        "Meeting Date": "Meeting Date: Sep 09, 2020 to Dec 11, 2020 Days: Mon Time: 08:35 - 11:25",
        "Also Register In": "Meeting Date: Sep 09, 2020 to Dec 11, 2020 Days: Fri Time: 10:05 - 11:25",
        "Other": "Also Register in:MAAE 4907 T1",
        "none": "Section Information:FSAE Synchronous course, meeting via web conferencing tools at scheduled time. Assignments, project and other activities will be completed outside of class."
    },
    {
        "Status": "Open",
        "CRN": "33846",
        "Course Number": "MAAE 4907",
        "Section": "E",
        "Title": "Engineering Design Project",
        "Credits": ".5",
        "Type": "Laboratory",
        "Restrictions": "Yes",
        "Prerequistes": "No",
        "Instructor Name": "John Gaydos",
        "Meeting Date": "Meeting Date: Sep 09, 2020 to Dec 11, 2020 Days: Mon Time: 10:05 - 11:25",
        "Also Register In": "Meeting Date: Sep 09, 2020 to Dec 11, 2020 Days: Fri Time: 08:35 - 11:25",
        "Other": "Also Register in:MAAE 4907 T1",
        "none": "Section Information:Carleton University Simulator Project Blended course: a mixture of synchronous meetings at scheduled time and asynchronouse activities. Students are expected to be available during the synchronous meeting times."
    },
    {
        "Status": "Open",
        "CRN": "33847",
        "Course Number": "MAAE 4907",
        "Section": "F",
        "Title": "Engineering Design Project",
        "Credits": ".5",
        "Type": "Laboratory",
        "Restrictions": "Yes",
        "Prerequistes": "No",
        "Instructor Name": "John Gaydos",
        "Meeting Date": "Meeting Date: Sep 09, 2020 to Dec 11, 2020 Days: Mon Time: 08:35 - 11:25",
        "Also Register In": "Meeting Date: Sep 09, 2020 to Dec 11, 2020 Days: Fri Time: 10:05 - 11:25",
        "Other": "Also Register in:MAAE 4907 T1",
        "none": "Section Information:Gas Turbine Synchronous course, meetings via web conferincing tools at scheduled time. Assignments, project and other activities will be completed outside of class."
    },
    {
        "Status": "Open",
        "CRN": "33848",
        "Course Number": "MAAE 4907",
        "Section": "G",
        "Title": "Engineering Design Project",
        "Credits": ".5",
        "Type": "Laboratory",
        "Restrictions": "Yes",
        "Prerequistes": "No",
        "Instructor Name": "John Gaydos",
        "Meeting Date": "Meeting Date: Sep 09, 2020 to Dec 11, 2020 Days: Mon Time: 10:05 - 11:25",
        "Also Register In": "Meeting Date: Sep 09, 2020 to Dec 11, 2020 Days: Fri Time: 08:35 - 11:25",
        "Other": "Also Register in:MAAE 4907 T1",
        "none": "Section Information:Integrated Autonomous Vehicle"
    },
    {
        "Status": "Open",
        "CRN": "33849",
        "Course Number": "MAAE 4907",
        "Section": "H",
        "Title": "Engineering Design Project",
        "Credits": ".5",
        "Type": "Laboratory",
        "Restrictions": "Yes",
        "Prerequistes": "No",
        "Instructor Name": "John Gaydos",
        "Meeting Date": "Meeting Date: Sep 09, 2020 to Dec 11, 2020 Days: Mon Time: 08:35 - 11:25",
        "Also Register In": "Meeting Date: Sep 09, 2020 to Dec 11, 2020 Days: Fri Time: 10:05 - 11:25",
        "Other": "Also Register in:MAAE 4907 T1",
        "none": "Section Information:Building Integrated Thermal Energy Systems"
    },
    {
        "Status": "Open",
        "CRN": "33850",
        "Course Number": "MAAE 4907",
        "Section": "I",
        "Title": "Engineering Design Project",
        "Credits": ".5",
        "Type": "Laboratory",
        "Restrictions": "Yes",
        "Prerequistes": "No",
        "Instructor Name": "John Gaydos",
        "Meeting Date": "Meeting Date: Sep 09, 2020 to Dec 11, 2020 Days: Mon Time: 10:05 - 11:25",
        "Also Register In": "Meeting Date: Sep 09, 2020 to Dec 11, 2020 Days: Fri Time: 08:35 - 11:25",
        "Other": "Also Register in:MAAE 4907 T1",
        "none": "Section Information:Crash Test Dummy project"
    },
    {
        "Status": "Open",
        "CRN": "33851",
        "Course Number": "MAAE 4907",
        "Section": "J",
        "Title": "Engineering Design Project",
        "Credits": ".5",
        "Type": "Laboratory",
        "Restrictions": "Yes",
        "Prerequistes": "No",
        "Instructor Name": "John Gaydos",
        "Meeting Date": "Meeting Date: Sep 09, 2020 to Dec 11, 2020 Days: Mon Time: 10:05 - 11:25",
        "Also Register In": "Meeting Date: Sep 09, 2020 to Dec 11, 2020 Days: Fri Time: 08:35 - 11:25",
        "Other": "Also Register in:MAAE 4907 T1",
        "none": "Section Information:Intelligent Telepresence and Assistive Devices Synchronous course, meetings via web conferencing tools at scheduled time. Assignments, project and other activities will be completed outside of class."
    },
    {
        "Status": "Open",
        "CRN": "33853",
        "Course Number": "MAAE 4907",
        "Section": "M",
        "Title": "Engineering Design Project",
        "Credits": ".5",
        "Type": "Laboratory",
        "Restrictions": "Yes",
        "Prerequistes": "No",
        "Instructor Name": "John Gaydos",
        "Meeting Date": "Meeting Date: Sep 09, 2020 to Dec 11, 2020 Days: Mon Time: 08:35 - 11:25",
        "Also Register In": "Meeting Date: Sep 09, 2020 to Dec 11, 2020 Days: Fri Time: 10:05 - 11:25",
        "Other": "Also Register in:MAAE 4907 T1",
        "none": "Section Information:Sustainable Energy Systems Portfolio"
    },
    {
        "Status": "Open",
        "CRN": "33854",
        "Course Number": "MAAE 4907",
        "Section": "T1",
        "Title": "Engineering Design Project",
        "Credits": "0",
        "Type": "Independent Study",
        "Restrictions": "No",
        "Prerequistes": "No",
        "Instructor Name": "John Gaydos",
        "Meeting Date": "Meeting Date: Sep 09, 2020 to Dec 11, 2020 Days: Fri Time: 13:05 - 14:25",
        "Also Register In": "Also Register in:MAAE 4907 A or B or C or D or E or F or G or H or I or J or M",
        "Other": "Section Information:Project Seminar"
    },
    {
        "Status": "Open",
        "CRN": "33855",
        "Course Number": "MAAE 4917",
        "Section": "B",
        "Title": "Undergraduate Directed Study",
        "Credits": ".5",
        "Type": "Directed Studies",
        "Restrictions": "Yes",
        "Prerequistes": "Yes",
        "Instructor Name": "Hanspeter Frei",
        "Meeting Date": "Meeting Date: Sep 09, 2020 to Dec 11, 2020 Days: Time:",
        "Also Register In": "none",
        "Other": "none"
    }
]
