[
    {
        "Status": "Open",
        "CRN": "34583",
        "Course Number": "PHYS 1001",
        "Section": "A",
        "Title": "Foundations of Physics I",
        "Credits": ".5",
        "Type": "Lecture",
        "Restrictions": "Yes",
        "Prerequistes": "Yes",
        "Instructor Name": "Thomas Gregoire",
        "Meeting Date": "Meeting Date: Sep 09, 2020 to Dec 11, 2020 Days: Tue Thu Time: 13:05 - 14:25",
        "Also Register In": "Also Register in:PHYS 1001 A1 or A2 or A4",
        "Other": "Section Information:Precludes additional credit for BIT 1002, BIT 1203, PHYS 1003, PHYS 1007"
    },
    {
        "Status": "Open",
        "CRN": "34584",
        "Course Number": "PHYS 1001",
        "Section": "A1",
        "Title": "Foundations of Physics I",
        "Credits": "0",
        "Type": "Laboratory",
        "Restrictions": "No",
        "Prerequistes": "No",
        "Instructor Name": "Igor Ivanovic",
        "Meeting Date": "Meeting Date: Sep 09, 2020 to Dec 11, 2020 Days: Wed Time: 14:35 - 17:25",
        "Also Register In": "Also Register in:PHYS 1001 A",
        "Other": "none"
    },
    {
        "Status": "Full, No Waitlist",
        "CRN": "34585",
        "Course Number": "PHYS 1001",
        "Section": "A2",
        "Title": "Foundations of Physics I",
        "Credits": "0",
        "Type": "Laboratory",
        "Restrictions": "No",
        "Prerequistes": "No",
        "Instructor Name": "Igor Ivanovic",
        "Meeting Date": "Meeting Date: Sep 09, 2020 to Dec 11, 2020 Days: Fri Time: 11:35 - 14:25",
        "Also Register In": "Also Register in:PHYS 1001 A",
        "Other": "none"
    },
    {
        "Status": "Full, No Waitlist",
        "CRN": "34587",
        "Course Number": "PHYS 1001",
        "Section": "A4",
        "Title": "Foundations of Physics I",
        "Credits": "0",
        "Type": "Laboratory",
        "Restrictions": "No",
        "Prerequistes": "No",
        "Instructor Name": "Igor Ivanovic",
        "Meeting Date": "Meeting Date: Sep 09, 2020 to Dec 11, 2020 Days: Mon Time: 08:35 - 11:25",
        "Also Register In": "Also Register in:PHYS 1001 A",
        "Other": "none"
    },
    {
        "Status": "Open",
        "CRN": "34588",
        "Course Number": "PHYS 1003",
        "Section": "A",
        "Title": "Mechanics and Thermodynamics",
        "Credits": ".5",
        "Type": "Lecture",
        "Restrictions": "Yes",
        "Prerequistes": "Yes",
        "Instructor Name": "Andrew Robinson",
        "Meeting Date": "Meeting Date: Sep 09, 2020 to Dec 11, 2020 Days: Wed Fri Time: 11:35 - 12:55",
        "Also Register In": "Also Register in:PHYS 1003 A4",
        "Other": "Section Information:Precludes additional credit for BIT 1002, BIT 1203, PHYS 1001, PHYS 1007"
    },
    {
        "Status": "Open",
        "CRN": "34591",
        "Course Number": "PHYS 1003",
        "Section": "A4",
        "Title": "Mechanics and Thermodynamics",
        "Credits": "0",
        "Type": "Laboratory",
        "Restrictions": "Yes",
        "Prerequistes": "No",
        "Instructor Name": "Benjamin Freestone",
        "Meeting Date": "Meeting Date: Sep 09, 2020 to Dec 11, 2020 Days: Mon Time: 11:35 - 14:25",
        "Also Register In": "Also Register in:PHYS 1003 A",
        "Other": "none"
    },
    {
        "Status": "Open",
        "CRN": "34594",
        "Course Number": "PHYS 1007",
        "Section": "A",
        "Title": "University Physics I",
        "Credits": ".5",
        "Type": "Lecture",
        "Restrictions": "Yes",
        "Prerequistes": "No",
        "Instructor Name": "Emily Heath",
        "Meeting Date": "Meeting Date: Sep 09, 2020 to Dec 11, 2020 Days: Mon Wed Time: 08:35 - 09:55",
        "Also Register In": "Also Register in:PHYS 1007 L1 or L2 or L3 or L4 or L5 or L6 or L7 or L9",
        "Other": "Section Information:Precludes additional credit for BIT 1002, BIT 1203, PHYS 1001, PHYS 1003. This course will be supported by Peer Assisted Study Sessions (PASS). Further information here: https://carleton.ca/csas/pass"
    },
    {
        "Status": "Open",
        "CRN": "34595",
        "Course Number": "PHYS 1007",
        "Section": "B",
        "Title": "University Physics I",
        "Credits": ".5",
        "Type": "Lecture",
        "Restrictions": "Yes",
        "Prerequistes": "No",
        "Instructor Name": "Andrew Robinson",
        "Meeting Date": "Meeting Date: Sep 09, 2020 to Dec 11, 2020 Days: Tue Thu Time: 13:05 - 14:25",
        "Also Register In": "Also Register in:PHYS 1007 L1 or L2 or L3 or L4 or L5 or L6 or L7 or L9",
        "Other": "Section Information:Precludes additional credit for BIT 1002, BIT 1203, PHYS 1001, PHYS 1003. This course will be supported by Peer Assisted Study Sessions (PASS). Further information here: https://carleton.ca/csas/pass"
    },
    {
        "Status": "Open",
        "CRN": "34596",
        "Course Number": "PHYS 1007",
        "Section": "L1",
        "Title": "University Physics I",
        "Credits": "0",
        "Type": "Laboratory",
        "Restrictions": "No",
        "Prerequistes": "No",
        "Instructor Name": "Tamara Rozina",
        "Meeting Date": "Meeting Date: Sep 09, 2020 to Dec 11, 2020 Days: Mon Time: 14:35 - 17:25",
        "Also Register In": "Also Register in:PHYS 1007 A or B",
        "Other": "none"
    },
    {
        "Status": "Open",
        "CRN": "34597",
        "Course Number": "PHYS 1007",
        "Section": "L2",
        "Title": "University Physics I",
        "Credits": "0",
        "Type": "Laboratory",
        "Restrictions": "No",
        "Prerequistes": "No",
        "Instructor Name": "Tamara Rozina",
        "Meeting Date": "Meeting Date: Sep 09, 2020 to Dec 11, 2020 Days: Tue Time: 08:35 - 11:25",
        "Also Register In": "Also Register in:PHYS 1007 A or B",
        "Other": "none"
    },
    {
        "Status": "Full, No Waitlist",
        "CRN": "34598",
        "Course Number": "PHYS 1007",
        "Section": "L3",
        "Title": "University Physics I",
        "Credits": "0",
        "Type": "Laboratory",
        "Restrictions": "No",
        "Prerequistes": "No",
        "Instructor Name": "Tamara Rozina",
        "Meeting Date": "Meeting Date: Sep 09, 2020 to Dec 11, 2020 Days: Thu Time: 08:35 - 11:25",
        "Also Register In": "Also Register in:PHYS 1007 A or B",
        "Other": "none"
    },
    {
        "Status": "Full, No Waitlist",
        "CRN": "34599",
        "Course Number": "PHYS 1007",
        "Section": "L4",
        "Title": "University Physics I",
        "Credits": "0",
        "Type": "Laboratory",
        "Restrictions": "No",
        "Prerequistes": "No",
        "Instructor Name": "Benjamin Freestone",
        "Meeting Date": "Meeting Date: Sep 09, 2020 to Dec 11, 2020 Days: Tue Time: 14:35 - 17:25",
        "Also Register In": "Also Register in:PHYS 1007 A or B",
        "Other": "none"
    },
    {
        "Status": "Full, No Waitlist",
        "CRN": "34600",
        "Course Number": "PHYS 1007",
        "Section": "L5",
        "Title": "University Physics I",
        "Credits": "0",
        "Type": "Laboratory",
        "Restrictions": "No",
        "Prerequistes": "No",
        "Instructor Name": "Benjamin Freestone",
        "Meeting Date": "Meeting Date: Sep 09, 2020 to Dec 11, 2020 Days: Wed Time: 11:35 - 14:25",
        "Also Register In": "Also Register in:PHYS 1007 A or B",
        "Other": "none"
    },
    {
        "Status": "Full, No Waitlist",
        "CRN": "34601",
        "Course Number": "PHYS 1007",
        "Section": "L6",
        "Title": "University Physics I",
        "Credits": "0",
        "Type": "Laboratory",
        "Restrictions": "No",
        "Prerequistes": "No",
        "Instructor Name": "Tamara Rozina",
        "Meeting Date": "Meeting Date: Sep 09, 2020 to Dec 11, 2020 Days: Fri Time: 08:35 - 11:25",
        "Also Register In": "Also Register in:PHYS 1007 A or B",
        "Other": "none"
    },
    {
        "Status": "Full, No Waitlist",
        "CRN": "34602",
        "Course Number": "PHYS 1007",
        "Section": "L7",
        "Title": "University Physics I",
        "Credits": "0",
        "Type": "Laboratory",
        "Restrictions": "No",
        "Prerequistes": "No",
        "Instructor Name": "Tamara Rozina",
        "Meeting Date": "Meeting Date: Sep 09, 2020 to Dec 11, 2020 Days: Fri Time: 14:35 - 17:25",
        "Also Register In": "Also Register in:PHYS 1007 A or B",
        "Other": "none"
    },
    {
        "Status": "Full, No Waitlist",
        "CRN": "34604",
        "Course Number": "PHYS 1007",
        "Section": "L9",
        "Title": "University Physics I",
        "Credits": "0",
        "Type": "Laboratory",
        "Restrictions": "No",
        "Prerequistes": "No",
        "Instructor Name": "Benjamin Freestone",
        "Meeting Date": "Meeting Date: Sep 09, 2020 to Dec 11, 2020 Days: Thu Time: 14:35 - 17:25",
        "Also Register In": "Also Register in:PHYS 1007 A or B",
        "Other": "none"
    },
    {
        "Status": "Open",
        "CRN": "34606",
        "Course Number": "PHYS 1901",
        "Section": "T",
        "Title": "Planetary Astronomy",
        "Credits": ".5",
        "Type": "Lecture",
        "Restrictions": "No",
        "Prerequistes": "No",
        "Instructor Name": "Razieh Enjilela",
        "Meeting Date": "Meeting Date: Sep 09, 2020 to Dec 11, 2020 Days: Time:",
        "Also Register In": "Section Information:Precludes additional credit for PHYS 2203 Rebroadcast of a previously recorded lecture; no required tune-in time. Info: Carleton Online",
        "Other": "none"
    },
    {
        "Status": "Open",
        "CRN": "34607",
        "Course Number": "PHYS 1905",
        "Section": "T",
        "Title": "Physics Behind Everyday Life",
        "Credits": ".5",
        "Type": "Lecture",
        "Restrictions": "No",
        "Prerequistes": "No",
        "Instructor Name": "Tong Xu",
        "Meeting Date": "Meeting Date: Sep 09, 2020 to Dec 11, 2020 Days: Time:",
        "Also Register In": "Section Information:Online Course. Designed for Web delivery. No on-campus classroom component. Further information here",
        "Other": "none"
    },
    {
        "Status": "Open",
        "CRN": "34609",
        "Course Number": "PHYS 2004",
        "Section": "A",
        "Title": "Modern Physics for Engineers",
        "Credits": ".5",
        "Type": "Lecture",
        "Restrictions": "Yes",
        "Prerequistes": "Yes",
        "Instructor Name": "Alain Bellerive",
        "Meeting Date": "Meeting Date: Sep 09, 2020 to Dec 11, 2020 Days: Wed Fri Time: 14:35 - 15:55",
        "Also Register In": "Section Information:Restricted to B.Eng. students not in the Eng/Phys Program. Students in programs other than B.Eng must obtain permission Precludes additional credit for PHYS 2604. Asynchronous course",
        "Other": "none"
    },
    {
        "Status": "Open",
        "CRN": "34610",
        "Course Number": "PHYS 2203",
        "Section": "A",
        "Title": "Astronomy",
        "Credits": ".5",
        "Type": "Lecture",
        "Restrictions": "No",
        "Prerequistes": "Yes",
        "Instructor Name": "Simon Viel",
        "Meeting Date": "Meeting Date: Sep 09, 2020 to Dec 11, 2020 Days: Mon Wed Time: 10:05 - 11:25",
        "Also Register In": "Section Information:Precludes additional credit for PHYS 1901 and PHYS 1902",
        "Other": "none"
    },
    {
        "Status": "Open",
        "CRN": "34611",
        "Course Number": "PHYS 2401",
        "Section": "A",
        "Title": "Thermal Physics",
        "Credits": ".5",
        "Type": "Lecture",
        "Restrictions": "No",
        "Prerequistes": "Yes",
        "Instructor Name": "Dag Gillberg",
        "Meeting Date": "Meeting Date: Sep 09, 2020 to Dec 11, 2020 Days: Wed Fri Time: 16:05 - 17:25",
        "Also Register In": "none",
        "Other": "none"
    },
    {
        "Status": "Open",
        "CRN": "34612",
        "Course Number": "PHYS 2604",
        "Section": "A",
        "Title": "Modern Physics I",
        "Credits": ".5",
        "Type": "Lecture",
        "Restrictions": "Yes",
        "Prerequistes": "Yes",
        "Instructor Name": "Alain Bellerive",
        "Meeting Date": "Meeting Date: Sep 09, 2020 to Dec 11, 2020 Days: Mon Wed Time: 08:35 - 09:55",
        "Also Register In": "Also Register in:PHYS 2604 A1 or A2 or A5 or A6",
        "Other": "Section Information:Precludes additional credit for PHYS 2004."
    },
    {
        "Status": "Full, No Waitlist",
        "CRN": "34613",
        "Course Number": "PHYS 2604",
        "Section": "A1",
        "Title": "Modern Physics I",
        "Credits": "0",
        "Type": "Laboratory",
        "Restrictions": "No",
        "Prerequistes": "No",
        "Instructor Name": "Maria Rozo Martinez",
        "Meeting Date": "Meeting Date: Sep 09, 2020 to Dec 11, 2020 Days: Tue Time: 14:35 - 17:25",
        "Also Register In": "Also Register in:PHYS 2604 A",
        "Other": "none"
    },
    {
        "Status": "Full, No Waitlist",
        "CRN": "34614",
        "Course Number": "PHYS 2604",
        "Section": "A2",
        "Title": "Modern Physics I",
        "Credits": "0",
        "Type": "Laboratory",
        "Restrictions": "No",
        "Prerequistes": "No",
        "Instructor Name": "Maria Rozo Martinez",
        "Meeting Date": "Meeting Date: Sep 09, 2020 to Dec 11, 2020 Days: Mon Time: 14:35 - 17:25",
        "Also Register In": "Also Register in:PHYS 2604 A",
        "Other": "none"
    },
    {
        "Status": "Full, No Waitlist",
        "CRN": "34616",
        "Course Number": "PHYS 2604",
        "Section": "A5",
        "Title": "Modern Physics I",
        "Credits": "0",
        "Type": "Laboratory",
        "Restrictions": "No",
        "Prerequistes": "No",
        "Instructor Name": "Maria Rozo Martinez",
        "Meeting Date": "Meeting Date: Sep 09, 2020 to Dec 11, 2020 Days: Fri Time: 08:35 - 11:25",
        "Also Register In": "Also Register in:PHYS 2604 A",
        "Other": "none"
    },
    {
        "Status": "Full, No Waitlist",
        "CRN": "34617",
        "Course Number": "PHYS 2604",
        "Section": "A6",
        "Title": "Modern Physics I",
        "Credits": "0",
        "Type": "Laboratory",
        "Restrictions": "No",
        "Prerequistes": "No",
        "Instructor Name": "Maria Rozo Martinez",
        "Meeting Date": "Meeting Date: Sep 09, 2020 to Dec 11, 2020 Days: Tue Time: 08:35 - 11:25",
        "Also Register In": "Also Register in:PHYS 2604 A",
        "Other": "none"
    },
    {
        "Status": "Full, No Waitlist",
        "CRN": "34618",
        "Course Number": "PHYS 3007",
        "Section": "A",
        "Title": "Third-Year Physics Lab. I",
        "Credits": ".5",
        "Type": "Laboratory",
        "Restrictions": "No",
        "Prerequistes": "Yes",
        "Instructor Name": "Thomas Koffas",
        "Meeting Date": "Meeting Date: Sep 09, 2020 to Dec 11, 2020 Days: Tue Thu Time: 08:35 - 11:25",
        "Also Register In": "Section Information:Precludes additional credit for PHYS 3008, PHYS 3009.",
        "Other": "none"
    },
    {
        "Status": "Open",
        "CRN": "34619",
        "Course Number": "PHYS 3007",
        "Section": "B",
        "Title": "Third-Year Physics Lab. I",
        "Credits": ".5",
        "Type": "Laboratory",
        "Restrictions": "No",
        "Prerequistes": "Yes",
        "Instructor Name": "Thomas Koffas",
        "Meeting Date": "Meeting Date: Sep 09, 2020 to Dec 11, 2020 Days: Wed Fri Time: 08:35 - 11:25",
        "Also Register In": "Section Information:Precludes additional credit for PHYS 3008, PHYS 3009.",
        "Other": "none"
    },
    {
        "Status": "Full, No Waitlist",
        "CRN": "34620",
        "Course Number": "PHYS 3009",
        "Section": "A",
        "Title": "3rd-Year Phys. Lab (AstroPhys)",
        "Credits": ".5",
        "Type": "Laboratory",
        "Restrictions": "Yes",
        "Prerequistes": "Yes",
        "Instructor Name": "Thomas Koffas",
        "Meeting Date": "Meeting Date: Sep 09, 2020 to Dec 11, 2020 Days: Tue Thu Time: 08:35 - 11:25",
        "Also Register In": "Section Information:Precludes additional credit for PHYS 3007, PHYS 3008.",
        "Other": "none"
    },
    {
        "Status": "Open",
        "CRN": "34621",
        "Course Number": "PHYS 3308",
        "Section": "A",
        "Title": "Electromagnetism",
        "Credits": ".5",
        "Type": "Lecture",
        "Restrictions": "No",
        "Prerequistes": "Yes",
        "Instructor Name": "Emily Heath",
        "Meeting Date": "Meeting Date: Sep 09, 2020 to Dec 11, 2020 Days: Wed Fri Time: 13:05 - 14:25",
        "Also Register In": "Section Information:Precludes additional credit for ELEC 3909.",
        "Other": "none"
    },
    {
        "Status": "Open",
        "CRN": "34622",
        "Course Number": "PHYS 3701",
        "Section": "A",
        "Title": "Elements of Quantum Mechanics",
        "Credits": ".5",
        "Type": "Lecture",
        "Restrictions": "No",
        "Prerequistes": "Yes",
        "Instructor Name": "Bruce Campbell",
        "Meeting Date": "Meeting Date: Sep 09, 2020 to Dec 11, 2020 Days: Tue Thu Time: 11:35 - 12:55",
        "Also Register In": "none",
        "Other": "none"
    },
    {
        "Status": "Open",
        "CRN": "34623",
        "Course Number": "PHYS 3802",
        "Section": "A",
        "Title": "Advanced Dynamics",
        "Credits": ".5",
        "Type": "Lecture",
        "Restrictions": "No",
        "Prerequistes": "Yes",
        "Instructor Name": "Razvan Gornea",
        "Meeting Date": "Meeting Date: Sep 09, 2020 to Dec 11, 2020 Days: Mon Wed Time: 14:35 - 15:55",
        "Also Register In": "none",
        "Other": "none"
    },
    {
        "Status": "Open",
        "CRN": "34625",
        "Course Number": "PHYS 4008",
        "Section": "A",
        "Title": "Fourth-Year Physics Lab. II",
        "Credits": ".5",
        "Type": "Laboratory",
        "Restrictions": "No",
        "Prerequistes": "Yes",
        "Instructor Name": "Sangeeta Murugkar",
        "Meeting Date": "Meeting Date: Sep 09, 2020 to Dec 11, 2020 Days: Tue Thu Time: 14:35 - 17:25",
        "Also Register In": "none",
        "Other": "none"
    },
    {
        "Status": "Open",
        "CRN": "34626",
        "Course Number": "PHYS 4203",
        "Section": "A",
        "Title": "Phys App of Fourier Analysis",
        "Credits": ".5",
        "Type": "Lecture",
        "Restrictions": "No",
        "Prerequistes": "Yes",
        "Instructor Name": "Paul Johns",
        "Meeting Date": "Meeting Date: Sep 09, 2020 to Dec 11, 2020 Days: Tue Thu Time: 11:35 - 12:55",
        "Also Register In": "none",
        "Other": "none"
    },
    {
        "Status": "Open",
        "CRN": "34628",
        "Course Number": "PHYS 4707",
        "Section": "A",
        "Title": "Intro. to Quantum Mechanics I",
        "Credits": ".5",
        "Type": "Lecture",
        "Restrictions": "No",
        "Prerequistes": "Yes",
        "Instructor Name": "Thomas Gregoire",
        "Meeting Date": "Meeting Date: Sep 09, 2020 to Dec 11, 2020 Days: Mon Wed Time: 10:05 - 11:25",
        "Also Register In": "none",
        "Other": "none"
    },
    {
        "Status": "Open",
        "CRN": "34629",
        "Course Number": "PHYS 4804",
        "Section": "A",
        "Title": "Intro. to General Relativity",
        "Credits": ".5",
        "Type": "Lecture",
        "Restrictions": "No",
        "Prerequistes": "Yes",
        "Instructor Name": "Daniel Stolarski",
        "Meeting Date": "Meeting Date: Sep 09, 2020 to Dec 11, 2020 Days: Tue Thu Time: 10:05 - 11:25",
        "Also Register In": "none",
        "Other": "none"
    },
    {
        "Status": "Full, No Waitlist",
        "CRN": "34630",
        "Course Number": "PHYS 4807",
        "Section": "A",
        "Title": "Computational Physics",
        "Credits": ".5",
        "Type": "Lecture",
        "Restrictions": "No",
        "Prerequistes": "No",
        "Instructor Name": "Dag Gillberg",
        "Meeting Date": "Meeting Date: Sep 09, 2020 to Dec 11, 2020 Days: Mon Wed Time: 14:35 - 15:55",
        "Also Register In": "Section Information:Same as PHYS 5002. Requires permission of the department. Ability to program in FORTAN, JAVA, C or C++",
        "Other": "none"
    },
    {
        "Status": "Open",
        "CRN": "35783",
        "Course Number": "PHYS 4907",
        "Section": "A",
        "Title": "Fourth-Year Project",
        "Credits": ".5",
        "Type": "Research Project",
        "Restrictions": "No",
        "Prerequistes": "No",
        "Instructor Name": "Bruce Campbell",
        "Meeting Date": "Meeting Date: Sep 09, 2020 to Dec 11, 2020 Days: Time:",
        "Also Register In": "none",
        "Other": "none"
    },
    {
        "Status": "Open",
        "CRN": "34631",
        "Course Number": "PHYS 4909",
        "Section": "A",
        "Title": "Fourth-Year Project",
        "Credits": ".5",
        "Type": "Research Project",
        "Restrictions": "No",
        "Prerequistes": "No",
        "Instructor Name": "Bruce Campbell",
        "Meeting Date": "Meeting Date: Sep 09, 2020 to Dec 11, 2020 Days: Time:",
        "Also Register In": "Section Information:Unscheduled/Requires permission of the department",
        "Other": "none"
    }
]
