[
    {
        "Status": "Full, No Waitlist",
        "CRN": "14950",
        "Course Number": "SOWK 5004",
        "Section": "W",
        "Title": "Group Work",
        "Credits": ".5",
        "Type": "Seminar",
        "Restrictions": "Yes",
        "Prerequistes": "No",
        "Instructor Name": "Meeting Date: Jan 06, 2020 to Apr 07, 2020 Days: Fri Time: 11:35 - 14:25 Building: Dunton Tower Room: 517",
        "Meeting Date": "Section Information:Group Work Core Course reserved for new Foundation Year MSW students.",
        "Also Register In": "none",
        "Other": "none"
    },
    {
        "Status": "Full, No Waitlist",
        "CRN": "14951",
        "Course Number": "SOWK 5013",
        "Section": "W",
        "Title": "Community-Based Partic. Resrch",
        "Credits": ".5",
        "Type": "Seminar",
        "Restrictions": "Yes",
        "Prerequistes": "No",
        "Instructor Name": "Pamela Grassau",
        "Meeting Date": "Meeting Date: Jan 06, 2020 to Apr 07, 2020 Days: Thu Time: 14:35 - 17:25 Building: Dunton Tower Room: 517",
        "Also Register In": "Section Information:Community Based Participatory Research Elective course reserved for Advanced Year MSW students",
        "Other": "none"
    },
    {
        "Status": "Open",
        "CRN": "14952",
        "Course Number": "SOWK 5014",
        "Section": "W",
        "Title": "Social Policy",
        "Credits": ".5",
        "Type": "Seminar",
        "Restrictions": "Yes",
        "Prerequistes": "No",
        "Instructor Name": "Melissa Redmond",
        "Meeting Date": "Meeting Date: Jan 06, 2020 to Apr 07, 2020 Days: Thu Time: 11:35 - 14:25 Building: Dunton Tower Room: 509A",
        "Also Register In": "Section Information:Social Policy Elective course reserved for Advanced Year MSW students",
        "Other": "none"
    },
    {
        "Status": "Full, No Waitlist",
        "CRN": "15355",
        "Course Number": "SOWK 5018",
        "Section": "A",
        "Title": "Adv Clinical Social Work Pract",
        "Credits": ".5",
        "Type": "Seminar",
        "Restrictions": "Yes",
        "Prerequistes": "No",
        "Instructor Name": "Joanne Doucette",
        "Meeting Date": "Meeting Date: Jan 06, 2020 to Apr 07, 2020 Days: Wed Time: 14:35 - 17:25 Building: Dunton Tower Room: 509A",
        "Also Register In": "Section Information:Advanced Clinical Social Work Practice Elective course reserved for Advanced Year MSW students with SOWK 5016 prerequisite Submit Registration Override Request for permission to register",
        "Other": "none"
    },
    {
        "Status": "Full, No Waitlist",
        "CRN": "14953",
        "Course Number": "SOWK 5020",
        "Section": "W",
        "Title": "Social Work Health Care Settin",
        "Credits": ".5",
        "Type": "Seminar",
        "Restrictions": "Yes",
        "Prerequistes": "No",
        "Instructor Name": "Bonnie Schroeder",
        "Meeting Date": "Meeting Date: Jan 06, 2020 to Apr 07, 2020 Days: Wed Time: 11:35 - 14:25 Building: Dunton Tower Room: 509A",
        "Also Register In": "Section Information:Social Work in Health Care Settings Elective course reserved for Advanced Year MSW students",
        "Other": "none"
    },
    {
        "Status": "Full, No Waitlist",
        "CRN": "14954",
        "Course Number": "SOWK 5302",
        "Section": "W",
        "Title": "Mental Health",
        "Credits": ".5",
        "Type": "Seminar",
        "Restrictions": "Yes",
        "Prerequistes": "No",
        "Instructor Name": "Nimo Bokore",
        "Meeting Date": "Meeting Date: Jan 06, 2020 to Apr 07, 2020 Days: Mon Time: 14:35 - 17:25 Building: Dunton Tower Room: 509A",
        "Also Register In": "none",
        "Other": "none"
    },
    {
        "Status": "Open",
        "CRN": "14955",
        "Course Number": "SOWK 5502",
        "Section": "W",
        "Title": "History of Social Welfare/Work",
        "Credits": ".5",
        "Type": "Seminar",
        "Restrictions": "Yes",
        "Prerequistes": "No",
        "Instructor Name": "Therese Jennissen",
        "Meeting Date": "Meeting Date: Jan 06, 2020 to Apr 07, 2020 Days: Tue Time: 14:35 - 17:25 Building: Dunton Tower Room: 517",
        "Also Register In": "Section Information:History of Social Work Elective course reserved for Advanced Year MSW students",
        "Other": "none"
    },
    {
        "Status": "Open",
        "CRN": "14956",
        "Course Number": "SOWK 5504",
        "Section": "F",
        "Title": "Directed Studies",
        "Credits": ".5",
        "Type": "Directed Studies",
        "Restrictions": "Yes",
        "Prerequistes": "No",
        "Instructor Name": "Susan Braedley",
        "Meeting Date": "Meeting Date: Jan 06, 2020 to Apr 07, 2020 Days: Time: Building: Room:",
        "Also Register In": "Section Information:2nd half of 1.0 credit Directed Study",
        "Other": "none"
    },
    {
        "Status": "Open",
        "CRN": "14958",
        "Course Number": "SOWK 5506",
        "Section": "W",
        "Title": "Directed Studies",
        "Credits": ".5",
        "Type": "Directed Studies",
        "Restrictions": "Yes",
        "Prerequistes": "No",
        "Instructor Name": "Susan Braedley",
        "Meeting Date": "Meeting Date: Jan 06, 2020 to Apr 07, 2020 Days: Time: Building: Room:",
        "Also Register In": "Section Information:0.5 credit Directed Studies Unscheduled/Requires Departmental permission More info:  https://carleton.ca/socialwork/msw-program/",
        "Other": "none"
    },
    {
        "Status": "Open",
        "CRN": "14959",
        "Course Number": "SOWK 5606",
        "Section": "A",
        "Title": "Practicum I",
        "Credits": "2",
        "Type": "Practicum",
        "Restrictions": "Yes",
        "Prerequistes": "No",
        "Instructor Name": "Brenda Morris",
        "Meeting Date": "Meeting Date: Jan 06, 2020 to Apr 07, 2020 Days: Fri Time: 08:35 - 11:25 Building: Paterson Hall Room: 234",
        "Also Register In": "Section Information:Unscheduled/Reserved for 1st (Foundation) Year MSW students",
        "Other": "none"
    },
    {
        "Status": "Open",
        "CRN": "14960",
        "Course Number": "SOWK 5606",
        "Section": "B",
        "Title": "Practicum I",
        "Credits": "2",
        "Type": "Practicum",
        "Restrictions": "Yes",
        "Prerequistes": "No",
        "Instructor Name": "Brenda Morris",
        "Meeting Date": "Meeting Date: Jan 06, 2020 to Apr 07, 2020 Days: Fri Time: 08:35 - 11:25 Building: Dunton Tower Room: 1006",
        "Also Register In": "Section Information:Unscheduled/Reserved for 1st (Foundation) Year MSW students",
        "Other": "none"
    },
    {
        "Status": "Open",
        "CRN": "14961",
        "Course Number": "SOWK 5606",
        "Section": "C",
        "Title": "Practicum I",
        "Credits": "2",
        "Type": "Practicum",
        "Restrictions": "Yes",
        "Prerequistes": "No",
        "Instructor Name": "Brenda Morris",
        "Meeting Date": "Meeting Date: Jan 06, 2020 to Apr 07, 2020 Days: Fri Time: 08:35 - 11:25 Building: Southam Hall Room: 408",
        "Also Register In": "Section Information:Unscheduled/Reserved for 1st (Foundation) Year MSW students",
        "Other": "none"
    },
    {
        "Status": "Open",
        "CRN": "14962",
        "Course Number": "SOWK 5606",
        "Section": "D",
        "Title": "Practicum I",
        "Credits": "2",
        "Type": "Practicum",
        "Restrictions": "Yes",
        "Prerequistes": "No",
        "Instructor Name": "Brenda Morris",
        "Meeting Date": "Meeting Date: Jan 06, 2020 to Apr 07, 2020 Days: Fri Time: 08:35 - 11:25 Building: Canal Building Room: 3102",
        "Also Register In": "none",
        "Other": "none"
    },
    {
        "Status": "Open",
        "CRN": "14963",
        "Course Number": "SOWK 5607",
        "Section": "A",
        "Title": "Practicum II",
        "Credits": "2",
        "Type": "Practicum",
        "Restrictions": "Yes",
        "Prerequistes": "No",
        "Instructor Name": "Brenda Morris",
        "Meeting Date": "Meeting Date: Jan 06, 2020 to Apr 07, 2020 Days: Fri Time: 08:35 - 11:25 Building: University Centre Room: 374",
        "Also Register In": "none",
        "Other": "none"
    },
    {
        "Status": "Full, No Waitlist",
        "CRN": "14964",
        "Course Number": "SOWK 5700",
        "Section": "W",
        "Title": "Immigration Policy",
        "Credits": ".5",
        "Type": "Seminar",
        "Restrictions": "Yes",
        "Prerequistes": "No",
        "Instructor Name": "Behnam Behnia",
        "Meeting Date": "Meeting Date: Jan 06, 2020 to Apr 07, 2020 Days: Mon Time: 11:35 - 14:25 Building: Dunton Tower Room: 509A",
        "Also Register In": "Section Information:Immigration Policy & Practice Elective course reserved for Advanced Year MSW students",
        "Other": "none"
    },
    {
        "Status": "Full, No Waitlist",
        "CRN": "14967",
        "Course Number": "SOWK 5703",
        "Section": "W",
        "Title": "Film, Television & Social Work",
        "Credits": ".5",
        "Type": "Seminar",
        "Restrictions": "Yes",
        "Prerequistes": "No",
        "Instructor Name": "Hugh Shewell",
        "Meeting Date": "Meeting Date: Jan 06, 2020 to Apr 07, 2020 Days: Tue Time: 08:35 - 11:25 Building: Dunton Tower Room: 517",
        "Also Register In": "Section Information:Elective course reserved for Advanced Year MSW students. Spc Topic - Film, Television & Social Work: Understanding Individual & Social Issues Through Media",
        "Other": "none"
    },
    {
        "Status": "Open",
        "CRN": "14968",
        "Course Number": "SOWK 5903",
        "Section": "G",
        "Title": "Independent Research Studies",
        "Credits": "1",
        "Type": "Independent Study",
        "Restrictions": "Yes",
        "Prerequistes": "No",
        "Instructor Name": "Susan Braedley",
        "Meeting Date": "Meeting Date: Jan 06, 2020 to Apr 07, 2020 Days: Time: Building: Room:",
        "Also Register In": "Section Information:1.0 credit Independent Research Study Unscheduled/Requires permission of the School of Social Work More info https://carleton.ca/socialwork/msw-program/",
        "Other": "none"
    },
    {
        "Status": "Open",
        "CRN": "14969",
        "Course Number": "SOWK 5904",
        "Section": "W",
        "Title": "Independent Research Studies",
        "Credits": ".5",
        "Type": "Independent Study",
        "Restrictions": "Yes",
        "Prerequistes": "No",
        "Instructor Name": "Susan Braedley",
        "Meeting Date": "Meeting Date: Jan 06, 2020 to Apr 07, 2020 Days: Time: Building: Room:",
        "Also Register In": "Section Information:0.5 credit Independent Research Study Unscheduled/Requires permission of the School of Socia Work More info https://carleton.ca/socialwork/msw-program/",
        "Other": "none"
    },
    {
        "Status": "Open",
        "CRN": "14970",
        "Course Number": "SOWK 5909",
        "Section": "W",
        "Title": "Thesis",
        "Credits": "0",
        "Type": "Masters Thesis",
        "Restrictions": "Yes",
        "Prerequistes": "No",
        "Instructor Name": "Susan Braedley",
        "Meeting Date": "Meeting Date: Jan 06, 2020 to Apr 07, 2020 Days: Time: Building: Room:",
        "Also Register In": "Section Information:Thesis Unscheduled/Requires permission of the School of Social Work",
        "Other": "none"
    },
    {
        "Status": "Open",
        "CRN": "14971",
        "Course Number": "SOWK 6102",
        "Section": "W",
        "Title": "Ethical Foundations",
        "Credits": ".5",
        "Type": "Seminar",
        "Restrictions": "Yes",
        "Prerequistes": "No",
        "Instructor Name": "Pamela Grassau",
        "Meeting Date": "Meeting Date: Jan 06, 2020 to Apr 07, 2020 Days: Wed Time: 11:35 - 14:25 Building: Dunton Tower Room: 625",
        "Also Register In": "Section Information:Ethical Foundations",
        "Other": "none"
    },
    {
        "Status": "Open",
        "CRN": "14974",
        "Course Number": "SOWK 6304",
        "Section": "W",
        "Title": "Ph.D. Seminar",
        "Credits": ".25",
        "Type": "Seminar",
        "Restrictions": "Yes",
        "Prerequistes": "No",
        "Instructor Name": "Susan Braedley",
        "Meeting Date": "Meeting Date: Jan 06, 2020 to Apr 07, 2020 Days: Tue Time: 11:35 - 14:25 Building: Dunton Tower Room: 625",
        "Also Register In": "Section Information:PhD Seminar",
        "Other": "none"
    },
    {
        "Status": "Open",
        "CRN": "14975",
        "Course Number": "SOWK 6405",
        "Section": "W",
        "Title": "Directed Studies",
        "Credits": ".5",
        "Type": "Directed Studies",
        "Restrictions": "No",
        "Prerequistes": "No",
        "Instructor Name": "Susan Braedley",
        "Meeting Date": "Meeting Date: Jan 06, 2020 to Apr 07, 2020 Days: Time: Building: Room:",
        "Also Register In": "Section Information:0.5 credit Directed Studies More info https://carleton.ca/socialwork/phd-program/",
        "Other": "none"
    },
    {
        "Status": "Open",
        "CRN": "14976",
        "Course Number": "SOWK 6600",
        "Section": "W",
        "Title": "Advocacy Practicum",
        "Credits": ".5",
        "Type": "Practicum",
        "Restrictions": "Yes",
        "Prerequistes": "No",
        "Instructor Name": "Susan Braedley",
        "Meeting Date": "Meeting Date: Jan 06, 2020 to Apr 07, 2020 Days: Time: Building: Room:",
        "Also Register In": "Section Information:Advocacy Practicum More info https://carleton.ca/socialwork/phd-program/",
        "Other": "none"
    },
    {
        "Status": "Open",
        "CRN": "14977",
        "Course Number": "SOWK 6800",
        "Section": "W",
        "Title": "Qualifying Examination",
        "Credits": ".5",
        "Type": "Other",
        "Restrictions": "Yes",
        "Prerequistes": "No",
        "Instructor Name": "Susan Braedley",
        "Meeting Date": "Meeting Date: Jan 06, 2020 to Apr 07, 2020 Days: Time: Building: Room:",
        "Also Register In": "Section Information:Qualifying Examination",
        "Other": "none"
    },
    {
        "Status": "Open",
        "CRN": "14978",
        "Course Number": "SOWK 6909",
        "Section": "W",
        "Title": "PhD Dissertation",
        "Credits": "0",
        "Type": "PhD Thesis",
        "Restrictions": "Yes",
        "Prerequistes": "No",
        "Instructor Name": "Susan Braedley",
        "Meeting Date": "Meeting Date: Jan 06, 2020 to Apr 07, 2020 Days: Time: Building: Room:",
        "Also Register In": "Section Information:PhD Dissertation",
        "Other": "none"
    }
]
