[
    {
        "Status": "Open",
        "CRN": "15296",
        "Course Number": "WGST 1808",
        "Section": "A",
        "Title": "Intro Women's & Gender Studies",
        "Credits": ".5",
        "Type": "Lecture",
        "Restrictions": "No",
        "Prerequistes": "No",
        "Instructor Name": "Katharine Bausch",
        "Meeting Date": "Meeting Date: Jan 06, 2020 to Apr 07, 2020 Days: Fri Time: 14:35 - 16:25 Building: Richcraft Hall Room: 2200",
        "Also Register In": "Also Register in:WGST 1808 A01 or A02 or A03 or A04 or A05 or A06 or A07 or A08 or A09",
        "Other": "Section Information:Introduction to Women's and Gender Studies"
    },
    {
        "Status": "Full, No Waitlist",
        "CRN": "15297",
        "Course Number": "WGST 1808",
        "Section": "A01",
        "Title": "Intro Women's & Gender Studies",
        "Credits": "0",
        "Type": "Discussion Group",
        "Restrictions": "No",
        "Prerequistes": "No",
        "Instructor Name": "Meeting Date: Jan 06, 2020 to Apr 07, 2020 Days: Mon Time: 09:35 - 10:25 Building: Tory Building Room: 204",
        "Meeting Date": "Also Register in:WGST 1808 A",
        "Also Register In": "none",
        "Other": "none"
    },
    {
        "Status": "Open",
        "CRN": "15298",
        "Course Number": "WGST 1808",
        "Section": "A02",
        "Title": "Intro Women's & Gender Studies",
        "Credits": "0",
        "Type": "Discussion Group",
        "Restrictions": "No",
        "Prerequistes": "No",
        "Instructor Name": "Meeting Date: Jan 06, 2020 to Apr 07, 2020 Days: Mon Time: 10:35 - 11:25 Building: Tory Building Room: 204",
        "Meeting Date": "Also Register in:WGST 1808 A",
        "Also Register In": "none",
        "Other": "none"
    },
    {
        "Status": "Open",
        "CRN": "15299",
        "Course Number": "WGST 1808",
        "Section": "A03",
        "Title": "Intro Women's & Gender Studies",
        "Credits": "0",
        "Type": "Discussion Group",
        "Restrictions": "No",
        "Prerequistes": "No",
        "Instructor Name": "Meeting Date: Jan 06, 2020 to Apr 07, 2020 Days: Mon Time: 09:35 - 10:25 Building: Richcraft Hall Room: 3112",
        "Meeting Date": "Also Register in:WGST 1808 A",
        "Also Register In": "none",
        "Other": "none"
    },
    {
        "Status": "Open",
        "CRN": "15300",
        "Course Number": "WGST 1808",
        "Section": "A04",
        "Title": "Intro Women's & Gender Studies",
        "Credits": "0",
        "Type": "Discussion Group",
        "Restrictions": "No",
        "Prerequistes": "No",
        "Instructor Name": "Meeting Date: Jan 06, 2020 to Apr 07, 2020 Days: Mon Time: 10:35 - 11:25 Building: Richcraft Hall Room: 3224",
        "Meeting Date": "Also Register in:WGST 1808 A",
        "Also Register In": "none",
        "Other": "none"
    },
    {
        "Status": "Open",
        "CRN": "15301",
        "Course Number": "WGST 1808",
        "Section": "A05",
        "Title": "Intro Women's & Gender Studies",
        "Credits": "0",
        "Type": "Discussion Group",
        "Restrictions": "No",
        "Prerequistes": "No",
        "Instructor Name": "Meeting Date: Jan 06, 2020 to Apr 07, 2020 Days: Tue Time: 14:35 - 15:25 Building: Residence Commons Room: 213",
        "Meeting Date": "Also Register in:WGST 1808 A",
        "Also Register In": "none",
        "Other": "none"
    },
    {
        "Status": "Open",
        "CRN": "15302",
        "Course Number": "WGST 1808",
        "Section": "A06",
        "Title": "Intro Women's & Gender Studies",
        "Credits": "0",
        "Type": "Discussion Group",
        "Restrictions": "No",
        "Prerequistes": "No",
        "Instructor Name": "Meeting Date: Jan 06, 2020 to Apr 07, 2020 Days: Tue Time: 15:35 - 16:25 Building: Tory Building Room: 230",
        "Meeting Date": "Also Register in:WGST 1808 A",
        "Also Register In": "none",
        "Other": "none"
    },
    {
        "Status": "Open",
        "CRN": "15303",
        "Course Number": "WGST 1808",
        "Section": "A07",
        "Title": "Intro Women's & Gender Studies",
        "Credits": "0",
        "Type": "Discussion Group",
        "Restrictions": "No",
        "Prerequistes": "No",
        "Instructor Name": "Meeting Date: Jan 06, 2020 to Apr 07, 2020 Days: Tue Time: 14:35 - 15:25 Building: Paterson Hall Room: 215",
        "Meeting Date": "Also Register in:WGST 1808 A",
        "Also Register In": "none",
        "Other": "none"
    },
    {
        "Status": "Open",
        "CRN": "15304",
        "Course Number": "WGST 1808",
        "Section": "A08",
        "Title": "Intro Women's & Gender Studies",
        "Credits": "0",
        "Type": "Discussion Group",
        "Restrictions": "No",
        "Prerequistes": "No",
        "Instructor Name": "Meeting Date: Jan 06, 2020 to Apr 07, 2020 Days: Tue Time: 15:35 - 16:25 Building: Residence Commons Room: 213",
        "Meeting Date": "Also Register in:WGST 1808 A",
        "Also Register In": "none",
        "Other": "none"
    },
    {
        "Status": "Full, No Waitlist",
        "CRN": "15305",
        "Course Number": "WGST 1808",
        "Section": "A09",
        "Title": "Intro Women's & Gender Studies",
        "Credits": "0",
        "Type": "Discussion Group",
        "Restrictions": "No",
        "Prerequistes": "No",
        "Instructor Name": "Meeting Date: Jan 06, 2020 to Apr 07, 2020 Days: Tue Time: 16:35 - 17:25 Building: Richcraft Hall Room: 3201",
        "Meeting Date": "Also Register in:WGST 1808 A",
        "Also Register In": "none",
        "Other": "none"
    },
    {
        "Status": "Open",
        "CRN": "15307",
        "Course Number": "WGST 1808",
        "Section": "B",
        "Title": "Intro Women's & Gender Studies",
        "Credits": ".5",
        "Type": "Lecture",
        "Restrictions": "No",
        "Prerequistes": "No",
        "Instructor Name": "Katharine Bausch",
        "Meeting Date": "Meeting Date: Jan 06, 2020 to Apr 07, 2020 Days: Wed Time: 18:05 - 19:55 Building: Tory Building Room: 360",
        "Also Register In": "Also Register in:WGST 1808 B01 or B02 or B03 or B04 or B05 or B06",
        "Other": "Section Information:Introduction to Women's and Gender Studies"
    },
    {
        "Status": "Full, No Waitlist",
        "CRN": "15308",
        "Course Number": "WGST 1808",
        "Section": "B01",
        "Title": "Intro Women's & Gender Studies",
        "Credits": "0",
        "Type": "Discussion Group",
        "Restrictions": "No",
        "Prerequistes": "No",
        "Instructor Name": "Meeting Date: Jan 06, 2020 to Apr 07, 2020 Days: Time: Building: Room:",
        "Meeting Date": "Also Register in:WGST 1808 B",
        "Also Register In": "Section Information:Online Web-Based Course CUOL",
        "Other": "none"
    },
    {
        "Status": "Open",
        "CRN": "15309",
        "Course Number": "WGST 1808",
        "Section": "B02",
        "Title": "Intro Women's & Gender Studies",
        "Credits": "0",
        "Type": "Discussion Group",
        "Restrictions": "No",
        "Prerequistes": "No",
        "Instructor Name": "Meeting Date: Jan 06, 2020 to Apr 07, 2020 Days: Time: Building: Room:",
        "Meeting Date": "Also Register in:WGST 1808 B",
        "Also Register In": "Section Information:Online Web-Based Course CUOL",
        "Other": "none"
    },
    {
        "Status": "Open",
        "CRN": "15310",
        "Course Number": "WGST 1808",
        "Section": "B03",
        "Title": "Intro Women's & Gender Studies",
        "Credits": "0",
        "Type": "Discussion Group",
        "Restrictions": "No",
        "Prerequistes": "No",
        "Instructor Name": "Meeting Date: Jan 06, 2020 to Apr 07, 2020 Days: Time: Building: Room:",
        "Meeting Date": "Also Register in:WGST 1808 B",
        "Also Register In": "Section Information:Online Web-Based Course CUOL",
        "Other": "none"
    },
    {
        "Status": "Open",
        "CRN": "15311",
        "Course Number": "WGST 1808",
        "Section": "B04",
        "Title": "Intro Women's & Gender Studies",
        "Credits": "0",
        "Type": "Discussion Group",
        "Restrictions": "No",
        "Prerequistes": "No",
        "Instructor Name": "Meeting Date: Jan 06, 2020 to Apr 07, 2020 Days: Time: Building: Room:",
        "Meeting Date": "Also Register in:WGST 1808 B",
        "Also Register In": "Section Information:Online Web-Based Course CUOL",
        "Other": "none"
    },
    {
        "Status": "Open",
        "CRN": "15312",
        "Course Number": "WGST 1808",
        "Section": "B05",
        "Title": "Intro Women's & Gender Studies",
        "Credits": "0",
        "Type": "Discussion Group",
        "Restrictions": "No",
        "Prerequistes": "No",
        "Instructor Name": "Meeting Date: Jan 06, 2020 to Apr 07, 2020 Days: Time: Building: Room:",
        "Meeting Date": "Also Register in:WGST 1808 B",
        "Also Register In": "Section Information:Online Web-Based Course CUOL",
        "Other": "none"
    },
    {
        "Status": "Open",
        "CRN": "15655",
        "Course Number": "WGST 1808",
        "Section": "B06",
        "Title": "Intro Women's & Gender Studies",
        "Credits": "0",
        "Type": "Discussion Group",
        "Restrictions": "No",
        "Prerequistes": "No",
        "Instructor Name": "Meeting Date: Jan 06, 2020 to Apr 07, 2020 Days: Time: Building: Room:",
        "Meeting Date": "Also Register in:WGST 1808 B",
        "Also Register In": "none",
        "Other": "none"
    },
    {
        "Status": "Open",
        "CRN": "15313",
        "Course Number": "WGST 2801",
        "Section": "A",
        "Title": "Activis,Femin. &  Social Justice",
        "Credits": ".5",
        "Type": "Lecture",
        "Restrictions": "Yes",
        "Prerequistes": "No",
        "Instructor Name": "Manjeet Birk",
        "Meeting Date": "Meeting Date: Jan 06, 2020 to Apr 07, 2020 Days: Thu Time: 14:35 - 16:25 Building: Southam Hall Room: 416",
        "Also Register In": "Also Register in:WGST 2801 A01 or A02 or A03 or A04",
        "Other": "Section Information:Prerequisite: Second-year Standing"
    },
    {
        "Status": "Full, No Waitlist",
        "CRN": "15314",
        "Course Number": "WGST 2801",
        "Section": "A01",
        "Title": "Activism Feminisms & Soci Justic",
        "Credits": "0",
        "Type": "Discussion Group",
        "Restrictions": "Yes",
        "Prerequistes": "No",
        "Instructor Name": "Meeting Date: Jan 06, 2020 to Apr 07, 2020 Days: Thu Time: 16:35 - 17:25 Building: Richcraft Hall Room: 3201",
        "Meeting Date": "Also Register in:WGST 2801 A",
        "Also Register In": "none",
        "Other": "none"
    },
    {
        "Status": "Full, No Waitlist",
        "CRN": "15315",
        "Course Number": "WGST 2801",
        "Section": "A02",
        "Title": "Activism Feminisms & Soci Justic",
        "Credits": "0",
        "Type": "Discussion Group",
        "Restrictions": "Yes",
        "Prerequistes": "No",
        "Instructor Name": "Meeting Date: Jan 06, 2020 to Apr 07, 2020 Days: Thu Time: 17:35 - 18:25 Building: Loeb Building Room: B243",
        "Meeting Date": "Also Register in:WGST 2801 A",
        "Also Register In": "none",
        "Other": "none"
    },
    {
        "Status": "Full, No Waitlist",
        "CRN": "15316",
        "Course Number": "WGST 2801",
        "Section": "A03",
        "Title": "Activism Feminisms & Soci Justic",
        "Credits": "0",
        "Type": "Discussion Group",
        "Restrictions": "Yes",
        "Prerequistes": "No",
        "Instructor Name": "Meeting Date: Jan 06, 2020 to Apr 07, 2020 Days: Thu Time: 16:35 - 17:25 Building: Leeds House Room: 118",
        "Meeting Date": "Also Register in:WGST 2801 A",
        "Also Register In": "none",
        "Other": "none"
    },
    {
        "Status": "Open",
        "CRN": "15317",
        "Course Number": "WGST 2801",
        "Section": "A04",
        "Title": "Activism Feminisms & Soci Justic",
        "Credits": "0",
        "Type": "Discussion Group",
        "Restrictions": "Yes",
        "Prerequistes": "No",
        "Instructor Name": "Meeting Date: Jan 06, 2020 to Apr 07, 2020 Days: Thu Time: 17:35 - 18:25 Building: Southam Hall Room: 311",
        "Meeting Date": "Also Register in:WGST 2801 A",
        "Also Register In": "none",
        "Other": "none"
    },
    {
        "Status": "Open",
        "CRN": "15318",
        "Course Number": "WGST 2812",
        "Section": "B",
        "Title": "Sel Topic: Sex for Sale",
        "Credits": ".5",
        "Type": "Lecture",
        "Restrictions": "Yes",
        "Prerequistes": "No",
        "Instructor Name": "Megan Rivers-Moore",
        "Meeting Date": "Meeting Date: Jan 06, 2020 to Apr 07, 2020 Days: Fri Time: 11:35 - 13:25 Building: Southam Hall Room: 416",
        "Also Register In": "Also Register in:WGST 2812 B01 or B02 or B03 or B04",
        "Other": "Section Information:Sex For Sale Prerequisite: Second-year Standing"
    },
    {
        "Status": "Open",
        "CRN": "15319",
        "Course Number": "WGST 2812",
        "Section": "B01",
        "Title": "Sel Topi: Women's & Gender Stud",
        "Credits": "0",
        "Type": "Discussion Group",
        "Restrictions": "Yes",
        "Prerequistes": "No",
        "Instructor Name": "Meeting Date: Jan 06, 2020 to Apr 07, 2020 Days: Wed Time: 09:35 - 10:25 Building: St. Patrick's Building Room: 412",
        "Meeting Date": "Also Register in:WGST 2812 B",
        "Also Register In": "none",
        "Other": "none"
    },
    {
        "Status": "Full, No Waitlist",
        "CRN": "15320",
        "Course Number": "WGST 2812",
        "Section": "B02",
        "Title": "Sel Topic: Sex Sells",
        "Credits": "0",
        "Type": "Discussion Group",
        "Restrictions": "Yes",
        "Prerequistes": "No",
        "Instructor Name": "Meeting Date: Jan 06, 2020 to Apr 07, 2020 Days: Mon Time: 12:35 - 13:25 Building: St. Patrick's Building Room: 415",
        "Meeting Date": "Also Register in:WGST 2812 B",
        "Also Register In": "none",
        "Other": "none"
    },
    {
        "Status": "Open",
        "CRN": "15321",
        "Course Number": "WGST 2812",
        "Section": "B03",
        "Title": "Sel Topi: Women's & Gender Stud",
        "Credits": "0",
        "Type": "Discussion Group",
        "Restrictions": "Yes",
        "Prerequistes": "No",
        "Instructor Name": "Meeting Date: Jan 06, 2020 to Apr 07, 2020 Days: Wed Time: 12:35 - 13:25 Building: Southam Hall Room: 408",
        "Meeting Date": "Also Register in:WGST 2812 B",
        "Also Register In": "none",
        "Other": "none"
    },
    {
        "Status": "Open",
        "CRN": "15322",
        "Course Number": "WGST 2812",
        "Section": "B04",
        "Title": "Sel Topic: Sex Sells",
        "Credits": "0",
        "Type": "Discussion Group",
        "Restrictions": "Yes",
        "Prerequistes": "No",
        "Instructor Name": "Meeting Date: Jan 06, 2020 to Apr 07, 2020 Days: Mon Time: 13:35 - 14:25 Building: Residence Commons Room: 212",
        "Meeting Date": "Also Register in:WGST 2812 B",
        "Also Register In": "none",
        "Other": "none"
    },
    {
        "Status": "Full, No Waitlist",
        "CRN": "15323",
        "Course Number": "WGST 2814",
        "Section": "A",
        "Title": "Gender,Sexuality,Cultural Prod",
        "Credits": ".5",
        "Type": "Lecture",
        "Restrictions": "Yes",
        "Prerequistes": "No",
        "Instructor Name": "Katharine Bausch",
        "Meeting Date": "Meeting Date: Jan 06, 2020 to Apr 07, 2020 Days: Tue Time: 14:35 - 16:25 Building: Southam Hall Room: 502",
        "Also Register In": "Also Register in:WGST 2814 A01 or A02 or A03",
        "Other": "Section Information:Gender, Sexuality and Cultural Production Prerequisite: Second-year Standing"
    },
    {
        "Status": "Full, No Waitlist",
        "CRN": "15324",
        "Course Number": "WGST 2814",
        "Section": "A01",
        "Title": "Gender,Sexuality & Cultur Produc",
        "Credits": "0",
        "Type": "Discussion Group",
        "Restrictions": "Yes",
        "Prerequistes": "No",
        "Instructor Name": "Meeting Date: Jan 06, 2020 to Apr 07, 2020 Days: Thu Time: 08:35 - 09:25 Building: Southam Hall Room: 313",
        "Meeting Date": "Also Register in:WGST 2814 A",
        "Also Register In": "none",
        "Other": "none"
    },
    {
        "Status": "Full, No Waitlist",
        "CRN": "15325",
        "Course Number": "WGST 2814",
        "Section": "A02",
        "Title": "Gender,Sexuality & Cultur Produc",
        "Credits": "0",
        "Type": "Discussion Group",
        "Restrictions": "Yes",
        "Prerequistes": "No",
        "Instructor Name": "Meeting Date: Jan 06, 2020 to Apr 07, 2020 Days: Thu Time: 09:35 - 10:25 Building: Southam Hall Room: 313",
        "Meeting Date": "Also Register in:WGST 2814 A",
        "Also Register In": "none",
        "Other": "none"
    },
    {
        "Status": "Open",
        "CRN": "15326",
        "Course Number": "WGST 2814",
        "Section": "A03",
        "Title": "Gender,Sexuality & Cultur Produc",
        "Credits": "0",
        "Type": "Discussion Group",
        "Restrictions": "Yes",
        "Prerequistes": "No",
        "Instructor Name": "Meeting Date: Jan 06, 2020 to Apr 07, 2020 Days: Thu Time: 08:35 - 09:25 Building: Richcraft Hall Room: 3110",
        "Meeting Date": "Also Register in:WGST 2814 A",
        "Also Register In": "none",
        "Other": "none"
    },
    {
        "Status": "Open",
        "CRN": "15327",
        "Course Number": "WGST 3810",
        "Section": "A",
        "Title": "Feminist Research",
        "Credits": ".5",
        "Type": "Lecture",
        "Restrictions": "Yes",
        "Prerequistes": "Yes",
        "Instructor Name": "Manjeet Birk",
        "Meeting Date": "Meeting Date: Jan 06, 2020 to Apr 07, 2020 Days: Tue Time: 14:35 - 17:25 Building: Canal Building Room: 3400",
        "Also Register In": "Section Information:Feminist Methods Prereq: WGST 3809 AND Third-year Stg in WGST Major or Minor Precludes additional credit for WOMN 3808 [1.0] (no longer o ffered).",
        "Other": "none"
    },
    {
        "Status": "Open",
        "CRN": "15328",
        "Course Number": "WGST 3812",
        "Section": "A",
        "Title": "Fem Activism and Social Media",
        "Credits": ".5",
        "Type": "Lecture",
        "Restrictions": "Yes",
        "Prerequistes": "No",
        "Instructor Name": "Katharine Kelly",
        "Meeting Date": "Meeting Date: Jan 06, 2020 to Apr 07, 2020 Days: Wed Time: 11:35 - 14:25 Building: Mackenzie Building Room: 4332",
        "Also Register In": "Section Information:Prerequisite: Third-year Standing and 1.0 cr. in WGST or Permission of the Institute",
        "Other": "none"
    },
    {
        "Status": "Open",
        "CRN": "15356",
        "Course Number": "WGST 3812",
        "Section": "B",
        "Title": "Disability & Transnationalism",
        "Credits": ".5",
        "Type": "Lecture",
        "Restrictions": "Yes",
        "Prerequistes": "No",
        "Instructor Name": "Natalie Spagnuolo",
        "Meeting Date": "Meeting Date: Jan 06, 2020 to Apr 07, 2020 Days: Tue Time: 14:35 - 17:25 Building: Tory Building Room: 236",
        "Also Register In": "none",
        "Other": "none"
    },
    {
        "Status": "Open",
        "CRN": "15331",
        "Course Number": "WGST 4811",
        "Section": "A",
        "Title": "Hons Research Project in WGST",
        "Credits": ".5",
        "Type": "Research Project",
        "Restrictions": "Yes",
        "Prerequistes": "Yes",
        "Instructor Name": "Meeting Date: Jan 06, 2020 to Apr 07, 2020 Days: Time: Building: Room:",
        "Meeting Date": "Section Information:Honours Research Project Prerequisite: Major CGPA of 11.0 AND WGST 3809 and WGST 3810 AND Fourth-year Standing or Permission of the Institute Required",
        "Also Register In": "none",
        "Other": "none"
    },
    {
        "Status": "Open",
        "CRN": "15333",
        "Course Number": "WGST 4812",
        "Section": "B",
        "Title": "Fem Pedagogy & Comm Mobilization",
        "Credits": ".5",
        "Type": "Seminar",
        "Restrictions": "Yes",
        "Prerequistes": "No",
        "Instructor Name": "Nadia Abu-Zahra",
        "Meeting Date": "Meeting Date: Jan 06, 2020 to Apr 07, 2020 Days: Tue Time: 11:35 - 14:25 Building: Paterson Hall Room: 234",
        "Also Register In": "Section Information:Topic Winter 2019: Prerequisite: Fourth-year standing and 1.0 cr in WGST courses or Permission of the Institute Piggy-backed with WGST 5902B",
        "Other": "none"
    },
    {
        "Status": "Full, No Waitlist",
        "CRN": "15334",
        "Course Number": "WGST 4812",
        "Section": "C",
        "Title": "Fem Controversies and the Law",
        "Credits": ".5",
        "Type": "Seminar",
        "Restrictions": "Yes",
        "Prerequistes": "No",
        "Instructor Name": "Ummni Khan",
        "Meeting Date": "Meeting Date: Jan 06, 2020 to Apr 07, 2020 Days: Wed Time: 11:35 - 14:25 Building: Southam Hall Room: 315",
        "Also Register In": "Section Information:Selected Topics: Prerequisite: Fourth-year standing AND 1.0 cr. in WGST courses OR Permission of the Institute This course is cross-listed with LAWS 4904B",
        "Other": "none"
    },
    {
        "Status": "Full, No Waitlist",
        "CRN": "15335",
        "Course Number": "WGST 4812",
        "Section": "D",
        "Title": "Sel Top: Transgender Cinema",
        "Credits": ".5",
        "Type": "Seminar",
        "Restrictions": "No",
        "Prerequistes": "No",
        "Instructor Name": "Laura Horak",
        "Meeting Date": "Meeting Date: Jan 06, 2020 to Apr 07, 2020 Days: Thu Time: 14:35 - 16:25 Building: St. Patrick's Building Room: 417",
        "Also Register In": "Also Register in:WGST 4812 DF",
        "Other": "none"
    },
    {
        "Status": "Full, No Waitlist",
        "CRN": "15336",
        "Course Number": "WGST 4812",
        "Section": "DF",
        "Title": "Sel Top: Transgender Cinema",
        "Credits": "0",
        "Type": "Film Screening",
        "Restrictions": "No",
        "Prerequistes": "No",
        "Instructor Name": "Laura Horak",
        "Meeting Date": "Meeting Date: Jan 06, 2020 to Apr 07, 2020 Days: Thu Time: 11:35 - 14:25 Building: St. Patrick's Building Room: 417",
        "Also Register In": "Also Register in:WGST 4812 D",
        "Other": "none"
    },
    {
        "Status": "Open",
        "CRN": "15357",
        "Course Number": "WGST 4812",
        "Section": "E",
        "Title": "Childhood & Youth in Afri Stdies",
        "Credits": ".5",
        "Type": "Seminar",
        "Restrictions": "Yes",
        "Prerequistes": "No",
        "Instructor Name": "Doris Kakuru",
        "Meeting Date": "Meeting Date: Jan 06, 2020 to Apr 07, 2020 Days: Thu Time: 08:35 - 11:25 Building: Richcraft Hall Room: 1201",
        "Also Register In": "none",
        "Other": "none"
    },
    {
        "Status": "Full, No Waitlist",
        "CRN": "15337",
        "Course Number": "WGST 4812",
        "Section": "W",
        "Title": "Queer (Meta) Fiction",
        "Credits": ".5",
        "Type": "Seminar",
        "Restrictions": "Yes",
        "Prerequistes": "No",
        "Instructor Name": "Jodie Medd",
        "Meeting Date": "Meeting Date: Jan 06, 2020 to Apr 07, 2020 Days: Wed Time: 08:35 - 11:25 Building: Dunton Tower Room: 1816",
        "Also Register In": "Section Information:Topic Winter 2020: Prerequisite: Fourth-year Standing AND 1.0 cr. in WGST or Permission of the Institute Piggy-backed with WGST 5902A",
        "Other": "none"
    },
    {
        "Status": "Open",
        "CRN": "15338",
        "Course Number": "WGST 4814",
        "Section": "W",
        "Title": "Independent Study",
        "Credits": ".5",
        "Type": "Independent Study",
        "Restrictions": "Yes",
        "Prerequistes": "No",
        "Instructor Name": "Megan Rivers-Moore",
        "Meeting Date": "Meeting Date: Jan 06, 2020 to Apr 07, 2020 Days: Time: Building: Room:",
        "Also Register In": "Section Information:Independent Study Prerequisite: Fourth-year Standing in WOMN AND Permission of the Institute Required",
        "Other": "none"
    }
]
